Workbook

Sheet Summary
A1: Multiship - QA bug list and coverage
A2: Prepared by Claude (Cowork) for Manoj on 2026-10-16. Counts on this sheet are formulas over the Bugs, Coverage and Screens sheets.
A4: Test details
A5: Application | B5: Multiship
A6: URL | B6: http://localhost:5173
A7: Environment | B7: Local dev (React/Vite UI, /api/v1 proxied to the Java backend); every carrier account in SANDBOX mode
A8: Build(s) tested | B8: local dev, 2026-10-13, local dev, 2026-10-13 (rebuilt after R4; frontend modules dated 13:12 IST), local dev, 2026-10-14 (order-form modules reloaded 13:17 IST), local dev, 2026-10-16
A9: Tested as (role) | B9: admin (ADMIN)
A10: Tested on | B10: 2026-10-11 to 2026-10-16
A11: Reference documents | B11: No SRS/FRD supplied. Expected behaviour taken from carrier API responses, the app's own messages and labels, and consistency between lanes and carriers
A12: Run R1 | B12: 2026-10-11 - Orders > New order: international shipments for client MKL246 to Canada, United Kingdom and Mexico, every carrier x service x packaging (FedEx, UPS, USPS); labels and Order API checked afterwards. Order references QA-1011-R13-*
A13: Run R2 | B13: 2026-10-12 - Settings > Organization (Clients, Warehouses, Address book, Users, Roles): every element of each list, add/edit form and detail view; rest of Settings mapped at menu level
A14: Run R3 | B14: 2026-10-12 - Retest of all 52 findings from R1 and R2 after the backend restart of 2026-10-12: each bug re-walked through its own steps in the interface
A15: Run R4 | B15: 2026-10-13 - Full re-walk of all 53 findings through their own steps, plus a first security and data-sanitation pass: input sanitation and output encoding, access control and tenant isolation, data integrity and storage hygiene, and session, transport and error handling
A16: Run R5 | B16: 2026-10-13 - Full regression of all 67 findings (BUG-001 to BUG-067), each re-walked through its own steps on the rebuilt build, plus an element-by-element pass of every Settings submodule (Organization, Carriers & Services, International, Labels & Documents, Email & Alerts, Integrations, System, Activity & Logs) with security, data-validation and data-sanitation checks on each screen
... A18: Run R7 | B18: 2026-10-16 - R7 retest: the 69 findings marked Fixed by the developers (Fixed in build 2026-10-15, HEAD 5f1d0e52) and the 7 Deferred (BUG-007, 017, 070, 088, 097, 123, 131), each re-walked through its own steps, with a check of neighbouring elements around each fix
A20: Coverage
A21: Screens mapped | B21: =COUNTA(Screens!$A:$A)-1 -> 41
A22: Screens: done | B22: =COUNTIF(Screens!$F:$F,"Done") -> 38
A23: Screens: partial | B23: =COUNTIF(Screens!$F:$F,"Partial") -> 3
A24: Screens: in progress | B24: =COUNTIF(Screens!$F:$F,"In progress") -> 0
A25: Screens: blocked | B25: =COUNTIF(Screens!$F:$F,"Blocked") -> 0
A26: Screens: not started | B26: =COUNTIF(Screens!$F:$F,"Not started") -> 0
A27: Elements listed | B27: =COUNTA(Coverage!$E:$E)-1 -> 438
A28: Elements: pass | B28: =COUNTIF(Coverage!$J:$J,"Pass") -> 344
A29: Elements: fail | B29: =COUNTIF(Coverage!$J:$J,"Fail") -> 67
A30: Elements: blocked | B30: =COUNTIF(Coverage!$J:$J,"Blocked") -> 18
A31: Elements: n/a | B31: =COUNTIF(Coverage!$J:$J,"N/A") -> 0
A32: Elements: not tested | B32: =COUNTIF(Coverage!$J:$J,"Not tested") -> 9
A33: Exercised (of testable elements) | B33: =IF(($B$27-$B$31)=0,0,($B$28+$B$29)/($B$27-$B$31)) -> 0.93835616
A35: Bugs found
A36: Critical | B36: =COUNTIFS(Bugs!$B:$B,"Critical",Bugs!$C:$C,"<>Query",Bugs!$C:$C,"<>Suggestion") -> 0
A37: High | B37: =COUNTIFS(Bugs!$B:$B,"High",Bugs!$C:$C,"<>Query",Bugs!$C:$C,"<>Suggestion") -> 9
A38: Medium | B38: =COUNTIFS(Bugs!$B:$B,"Medium",Bugs!$C:$C,"<>Query",Bugs!$C:$C,"<>Suggestion") -> 44
A39: Low | B39: =COUNTIFS(Bugs!$B:$B,"Low",Bugs!$C:$C,"<>Query",Bugs!$C:$C,"<>Suggestion") -> 94
A40: Total defects | B40: =SUM($B$36:$B$39) -> 147
A41: Queries (need a decision) | B41: =COUNTIF(Bugs!$C:$C,"Query") -> 11
A42: Suggestions | B42: =COUNTIF(Bugs!$C:$C,"Suggestion") -> 4
A44: Fix progress (changes as the Dev status and Tester status columns are updated)
A45: Dev status: New | B45: =COUNTIF(Bugs!$Z:$Z,"New") -> 65
A46: Dev status: In progress | B46: =COUNTIF(Bugs!$Z:$Z,"In progress") -> 0
A47: Dev status: Fixed | B47: =COUNTIF(Bugs!$Z:$Z,"Fixed") -> 90
A48: Dev status: Not a bug | B48: =COUNTIF(Bugs!$Z:$Z,"Not a bug") -> 0
A49: Dev status: Cannot reproduce | B49: =COUNTIF(Bugs!$Z:$Z,"Cannot reproduce") -> 0
A50: Dev status: Deferred | B50: =COUNTIF(Bugs!$Z:$Z,"Deferred") -> 7
A51: Dev status: Duplicate | B51: =COUNTIF(Bugs!$Z:$Z,"Duplicate") -> 0
A52: Tester status: Open | B52: =COUNTIF(Bugs!$X:$X,"Open") -> 15
A53: Tester status: Reopened | B53: =COUNTIF(Bugs!$X:$X,"Reopened") -> 26
A54: Tester status: Closed | B54: =COUNTIF(Bugs!$X:$X,"Closed") -> 121
A56: Defects by module
A57: Module | B57: Critical | C57: High | D57: Medium | E57: Low | F57: Total
A58: Orders | B58: =COUNTIFS(Bugs!$D:$D,$A58,Bugs!$B:$B,"Critical",Bugs!$C:$C,"<>Query",Bugs!$C:$C,"<>Suggestion") -> 0 | C58: =COUNTIFS(Bugs!$D:$D,$A58,Bugs!$B:$B,"High",Bugs!$C:$C,"<>Query",Bugs!$C:$C,"<>Suggestion") -> 3 | D58: =COUNTIFS(Bugs!$D:$D,$A58,Bugs!$B:$B,"Medium",Bugs!$C:$C,"<>Query",Bugs!$C:$C,"<>Suggestion") -> 8 | E58: =COUNTIFS(Bugs!$D:$D,$A58,Bugs!$B:$B,"Low",Bugs!$C:$C,"<>Query",Bugs!$C:$C,"<>Suggestion") -> 17 | F58: =SUM(B58:E58) -> 28
A59: API | B59: =COUNTIFS(Bugs!$D:$D,$A59,Bugs!$B:$B,"Critical",Bugs!$C:$C,"<>Query",Bugs!$C:$C,"<>Suggestion") -> 0 | C59: =COUNTIFS(Bugs!$D:$D,$A59,Bugs!$B:$B,"High",Bugs!$C:$C,"<>Query",Bugs!$C:$C,"<>Suggestion") -> 0 | D59: =COUNTIFS(Bugs!$D:$D,$A59,Bugs!$B:$B,"Medium",Bugs!$C:$C,"<>Query",Bugs!$C:$C,"<>Suggestion") -> 0 | E59: =COUNTIFS(Bugs!$D:$D,$A59,Bugs!$B:$B,"Low",Bugs!$C:$C,"<>Query",Bugs!$C:$C,"<>Suggestion") -> 3 | F59: =SUM(B59:E59) -> 3
A60: Settings | B60: =COUNTIFS(Bugs!$D:$D,$A60,Bugs!$B:$B,"Critical",Bugs!$C:$C,"<>Query",Bugs!$C:$C,"<>Suggestion") -> 0 | C60: =COUNTIFS(Bugs!$D:$D,$A60,Bugs!$B:$B,"High",Bugs!$C:$C,"<>Query",Bugs!$C:$C,"<>Suggestion") -> 6 | D60: =COUNTIFS(Bugs!$D:$D,$A60,Bugs!$B:$B,"Medium",Bugs!$C:$C,"<>Query",Bugs!$C:$C,"<>Suggestion") -> 36 | E60: =COUNTIFS(Bugs!$D:$D,$A60,Bugs!$B:$B,"Low",Bugs!$C:$C,"<>Query",Bugs!$C:$C,"<>Suggestion") -> 73 | F60: =SUM(B60:E60) -> 115
A61: App shell | B61: =COUNTIFS(Bugs!$D:$D,$A61,Bugs!$B:$B,"Critical",Bugs!$C:$C,"<>Query",Bugs!$C:$C,"<>Suggestion") -> 0 | C61: =COUNTIFS(Bugs!$D:$D,$A61,Bugs!$B:$B,"High",Bugs!$C:$C,"<>Query",Bugs!$C:$C,"<>Suggestion") -> 0 | D61: =COUNTIFS(Bugs!$D:$D,$A61,Bugs!$B:$B,"Medium",Bugs!$C:$C,"<>Query",Bugs!$C:$C,"<>Suggestion") -> 0 | E61: =COUNTIFS(Bugs!$D:$D,$A61,Bugs!$B:$B,"Low",Bugs!$C:$C,"<>Query",Bugs!$C:$C,"<>Suggestion") -> 1 | F61: =SUM(B61:E61) -> 1
A63: Tester's notes
A64: Limitation (R1) | B64: No SRS / FRD was supplied. Expected behaviour comes from the carrier responses, the app's own messages and tooltips, and consistency between lanes and carriers; findings with weaker footing are logged as Query or Suggestion.
A65: Limitation (R1) | B65: Combination run, not an element-by-element pass: every carrier x service x packaging the app offers was shipped to Canada, the UK and Mexico (128 orders on 2026-10-11). Controls not needed for that were not exercised and show as Not tested (Duties paid by, Currency, Pickup type, AES ITN, SKU, Tax ID, EORI, Commercial Invoice tab, label downloads, tracking and print).
A66: Limitation (R1) | B66: R1's screenshots and network timings come from a validate-only evidence pass on 2026-10-12 that generated no labels and created no orders; the first order number after the run, #934191, was still free at that point and was later used by the retest. Console output was not captured. BUG-011 and BUG-016 were seen once during the run and have no screenshot.
A67: Limitation (R1) | B67: All carrier accounts are in sandbox mode: FedEx rate calls often failed (HTTP 500 / 503, shown as 'No price ... to review') and label documents are sandbox samples, so per-box label content could not be verified.
A68: Observation (R1) | B68: Retest on 2026-10-12 of an empty Mexico State / region showed a toast and a red field; the run notes had recorded Validate doing nothing visible, so that part is not reported. Also seen in sandbox: FedEx Envelope rating returned HTTP 400 (dimensions under 1 in), and each label page sends its /label requests twice (likely React StrictMode in the dev build).
A69: Summary (R1) | B69: International shipping works end to end for all three carriers once the inputs suit each carrier: every one of the 114 carrier x service x packaging combinations produced a label for Canada, the UK and Mexico, and the Order API matches the screens for all 128 orders. What worries me most is that the shipment check passes shipments the carrier then rejects, so problems only surface as ERROR orders: USPS international fails with MKL246's default sender name and when a second box has no customs lines (where box 1 may already be booked), and single-piece FedEx and UPS packagings accept a second box. The FedEx International Priority check also raises a false 'issue to fix' on every IP shipment yet lets the label through, which teaches users to ignore the check. Fix first: BUG-001, BUG-002 and BUG-003, then BUG-004 and BUG-005.
A70: Limitation (R2) | B70: R2 covers Settings > Organization only: Clients (list and the 8-step Add/Edit wizard), Warehouses, Address book, Users and Roles, plus the All settings overview. The other 31 Settings screens are mapped in the application map but not yet tested.
A71: Limitation (R2) | B71: Settings > Address book could not be exercised: its only data call returns 500 every time (BUG-044), so the search, the client filter, the grid and the row actions are recorded as blocked rather than tested.
A72: Limitation (R2) | B72: On Settings > Users the per-row Role control, Reset password and Deactivate were not exercised. The only accounts are the signed-in admin and one real person's account, and the test invitation sent for the purpose never produced a user row (BUG-050). Deactivate on the admin row was deliberately not clicked at the user's request - it is reported as a risk in BUG-051.
A73: Limitation (R2) | B73: CSV exports: the user allowed the downloads, and the request, its parameters and the response were checked for each one, but the downloaded files themselves could not be opened from this session, so their contents are unverified.
A74: Observation (R2) | B74: Carrier address validation was run once per carrier on the warehouse panel with the user's explicit go-ahead. All three sandbox accounts answered NOT_SUPPORTED for want of live credentials, so no address was actually checked against a carrier and the warehouse address rules (BUG-040) go unenforced end to end.
A75: Observation (R2) | B75: Settings > Mail reports 'No provider active - outbound emails are logged only' and has no registered providers, so nothing sent from Settings in this environment can reach an inbox. The one invitation sent during the run therefore went nowhere.
... A106: Observation (R7) | B106: R7: Writeback Journal (neighbour of BUG-134): Retry is still offered on all 283 Skipped rows although the page says 'Retry any failed row'. That may be deliberate - to re-fire once the target connection is active - but the page does not say so; please confirm. Retry was not clicked.
A108: How to use this workbook
A109: Bugs sheet: one row per bug. Developers fill only the yellow columns - Dev status, Assigned to, Developer comments, Fixed in build. Please do not change Bug ID.
A110: Coverage sheet: every element that was listed on every screen tested, with its result, what was tried and the requirement it was checked against. Filter on Requirement ref to see what has been verified for a clause.
A111: Screens sheet: the application map and how far testing has reached on each screen.
A112: Send this workbook back for retest: the tester reads the Dev status column and re-checks every bug marked Fixed.
A113: The hidden sheet '_ledger' holds the test records so that testing can resume from this file. Please do not delete it.

Sheet Bugs
A1: Bug ID | B1: Severity | C1: Type | D1: Module | E1: Submodule | F1: Screen | G1: Element | H1: Title | I1: Steps to reproduce | J1: Test data | K1: Expected result | L1: Actual result | M1: Technical evidence | N1: URL | O1: Reproducibility | P1: Screenshots | Q1: Requirement ref | R1: Role | S1: Build | T1: Found on | U1: Run | V1: Screen ID | W1: Also affects | X1: Tester status | Y1: Retest notes | Z1: Dev status | AA1: Assigned to | AB1: Developer comments | AC1: Fixed in build
A2: BUG-001 | B2: High | C2: Validation | D2: Orders | E2: New order | F2: New order form (international) | G2: Ship-from Full name | H2: New shipment (USPS international): label fails for MKL246's default sender name 'MKL'; the shipment check passes it | I2: 1. Open Orders and click + New shipment (/orders/new) 2. Client: MKL246 (ship from 3PL-EAST, the client default); leave Ship from Full name as the profile default 'MKL' 3. Carrier: USPS 4. Ship to: Full name QA Test Recipient, Company QA Test Co, Address line 1 Av Paseo de la Reforma 222, Country Mexico (MX), Phone 5552081234, State / region CMX, City Ciudad de Mexico, Postal code 06600 5. Service level: USPS Priority Mail Intl 6. Packaging THB-PACKAGE, Weight 5; click Add another box, then Apply box 1 to all 7. Customs: Reason of export Sale, FTR exemption NOEEI 30.37(a), Label type PDF, Incoterms DAP 8. Importer of record & customs broker > Add: Type Receiver, Name and Contact QA Test Recipient, same address, city, post code and phone as Ship to > Use for this shipment 9. Items: Description Cotton T-shirt, HS code 61091000, Origin US, Qty 2, Unit value 20.00, Wt 0.5 10. Click Validate shipment 11. Click Generate label | J2: Ship-from Full name 'MKL' (MKL246 profile default). Orders #934105 (Canada, PMI), #934109 (Canada, PMEI), #934147 (UK, PMI), #934186 (Mexico, PMI) | K2: Either the label is created, or the shipment check flags before Generate that USPS international needs a sender full name of first and last name (two words of 2+ letters). | L2: Check said 'Ready to ship — 1 thing to review: USPS normalised the address; review before shipping.' (Canada: 'All checks passed'). Generate label then shows 'The carrier rejected this shipment If provided, fullname must contain at least 2 alphabetic characters, followed by a space, followed by at least another 2 alphabetic characters. (saved as order 934186)' and the order is saved as ERROR. Same result 4 of 4 times (Canada, UK, Mexico; Priority Mail Intl and Priority Mail Express Intl). With Full name changed to 'MKL Shipping' the same shipments generate (#934107, #934108, #934110-#934112, #934148-#934151, #934187-#934190). | M2: GET /api/v1/orders/934186 -> errorDetails.errorMessage 'STAMPS createShipmentSera[pkg 1/2] HTTP 400 ... fullname must contain at least 2 alphabetic characters ...' (Canada #934105: Stamps code 6619409). Orders list shows ERR with tooltip 'CARRIER If provided, fullname must contain ...'. | N2: /orders/new | O2: Always (4 of 4) | P2: BUG-001.jpg, BUG-001-2.jpg, BUG-001-3.jpg | R2: admin (ADMIN) | T2: 2026-10-11 | U2: R1 | V2: S001 | X2: Closed | Y2: 2026-10-12 R3: still-failing - Confirmed with one SANDBOX label, with Manoj's permission. USPS Priority Mail Intl, MKL246 to 1 Canada Square, London E14 5AB, GB, Ship from Full name left at the client default 'MKL'. The check reported 'Ready to ship - 1 thing to review' with Addresses, Package & weight, Account/service/price and Customs all Passed, and Generate label was enabled. Generate then produced the red toast 'The carrier rejected this shipment - If provided, fullname must contain at least 2 alphabetic characters, followed by a space, followed by at least another 2 alphabetic characters. (saved as order 934191)'. GET /api/v1/orders/934191 shows status ERROR with 'STAMPS createShipmentSera[pkg 1/2] HTTP 400 ... error_code 6619409'. The only change is that the toast now names the order it saved. 2026-10-13 R4 (build local dev, 2026-10-13): still-failing - The pre-flight guard is still absent. USPS Priority Mail Intl, MKL246 to 1 Canada Square, London E14 5AB GB, with Ship from Full name left at the client default 'MKL': the check returns 'Ready to ship - 1 thing to review' with Addresses, Package & weight, Account/service/price and Customs all Passed, and Generate label is enabled. No check mentions the sender name. The carrier rejection itself was not re-provoked today - it was confirmed on 2026-10-12 with order #934191 (STAMPS HTTP 400, error_code 6619409) and nothing in the form has changed, so a second order was not spent on it. 2026-10-13 R5 (build local dev, 2026-10-13 (rebuilt after R4; frontend modules dated 13:12 IST)): fixed - Fixed by outcome. USPS Priority Mail Intl, MKL246 to 1 Canada Square, London E14 5AB GB, 2 x THB-PACKAGE 5 lb, Ship from Full name left at the client default 'MKL' (the validate request carries shipFrom.name 'MKL'). The check still does not mention the sender name - it returns 'Ready to ship - 1 thing to review' with Addresses Passed and localErrors [] - but Generate label now succeeds: order #934192 (reference QA-1013-R5-GB-US-PMI-MKL) was created as GENERATED with tracking CJ000000005US and no errorDetails, where #934191 was refused by Stamps with error 6619409 on the same lane. The bug allowed either outcome ('the label is created, or the check flags it'), and the label is now created. Note for the developers: the 'USPS international needs a sender full name' message described in the fix was not seen anywhere in the interface on this lane. | Z2: Fixed | AB2: Fixed on dev (70ae2636): SERA fullname guard shipped 2026-10-12; verified via curl: validate returns "USPS international needs a sender full name" as sender.name error. QA R4 ran against stale FE bundle. Rebuild + retest. | AC2: 2026-10-13
A3: BUG-002 | B3: High | C3: Functional | D3: Orders | E3: New order | F3: New order form (international) | G3: Item Pkg# | H3: New shipment (USPS international, 2 boxes): with all item lines in box 1, box 2 fails 'Missing customs lines' after box 1 already went to the carrier | I3: 1. Open Orders and click + New shipment (/orders/new) 2. Client: MKL246 (ship from 3PL-EAST, the client default); set Ship from Full name to 'MKL Shipping' 3. Carrier: USPS 4. Ship to: QA Test Recipient, QA Test Co, Toronto ON M5V 3L9, Canada (as for the other Canada orders of the run) 5. Service level: USPS Priority Mail Intl 6. Packaging THB-PACKAGE, Weight 5; Add another box; Apply box 1 to all 7. Customs: Reason of export Sale, Label type PDF, Incoterms DAP 8. Importer of record & customs broker > Add: Type Receiver, Name and Contact QA Test Recipient, same address, city, post code and phone as Ship to > Use for this shipment 9. Items: one line Cotton T-shirt, HS 61091000, Origin US, Qty 2, Unit value 20.00, Wt 0.5; leave Boxes on 'All in box 1' (Pkg # 1) 10. Click Validate shipment, then Generate label | J3: Order #934106 (QA-1011-R13-CA-US-PMI-THB-NM) | K3: The check warns that USPS needs customs lines on every box (or the lines are split across the boxes automatically) before the label is bought; nothing is booked for part of the shipment. | L3: Check: 'All checks passed'. Generate label: 'Missing customs lines.'; order #934106 saved as ERROR. The error names package 2 of 2, so package 1 had already passed its carrier call; the app shows nothing about whether package 1 was booked or voided at USPS (not verified). With two lines of Qty 1 spread across the boxes (Spread across 2 boxes) the same shipment generates (#934108, #934110-#934112, #934148-#934151, #934187-#934190). | M3: GET /api/v1/orders/934106 -> errorDetails.errorMessage 'STAMPS createShipmentSera[pkg 2/2] HTTP 400 ... Missing customs lines.' | N3: /orders/new | O3: 1 of 1 (not repeated, to avoid further carrier bookings) | P3: BUG-002.jpg, BUG-002-2.jpg, BUG-002-3.png | R3: admin (ADMIN) | T3: 2026-10-11 | U3: R1 | V3: S001 | X3: Closed | Y3: 2026-10-12 R3: fixed - The pre-flight now catches it. With two boxes and every item line in box 1, the check reports '1 issue to fix before the label can be bought' and under Package & weight: 'Box 2 has no customs lines. Every box in a multi-box international shipment needs at least one item - redistribute items or remove the box.' Generate label stays disabled and Carrier check reads 'Not checked', so nothing is sent to the carrier. After spreading the lines across the boxes the check passes. Nothing is now booked for part of a shipment. 2026-10-13 R4 (build local dev, 2026-10-13): fixed - Re-walked. With two boxes and every item line put in box 1, the check returns '1 issue to fix before the label can be bought' and under Package & weight: 'Box 2 has no customs lines. Every box in a multi-box international shipment needs at least one item - redistribute items or remove the box.' Generate label stays disabled and Carrier check reads 'Not checked', so the carrier is never called for a part-filled shipment. 2026-10-13 R5 (build local dev, 2026-10-13 (rebuilt after R4; frontend modules dated 13:12 IST)): fixed - Regression check passed. Same USPS shipment to London with two boxes and the only item line in box 1: the check returns '1 issue to fix before the label can be bought' with Package & weight 'Box 2 has no customs lines. Every box in a multi-box international shipment needs at least one item - redistribute items or remove the box.', Carrier check 'Not checked' and Generate label disabled. | Z3: New
A4: BUG-003 | B4: Medium | C4: Validation | D4: Orders | E4: New order | F4: New order form (international) | G4: Add another box | H4: New shipment: single-piece carrier packagings (FedEx Envelope, 10kg, 25kg box; UPS 10KG, 25KG box) accept a second box, then the carrier rejects the label | I4: 1. Open Orders and click + New shipment (/orders/new) 2. Client: MKL246 (ship from 3PL-EAST, the client default) 3. Carrier: FedEx 4. Ship to: QA Test Recipient, Toronto ON M5V 3L9, Canada 5. Service level: FedEx International Priority 6. Packaging FedEx 10kg Box, Weight 10 7. Click Add another box, then Apply box 1 to all (2 boxes) 8. Customs: Reason of export Sale, Export declaration ref 'NO EEI 30.36', Label type PDF, Label size Paper 4x6, Incoterms DAP 9. Importer of record & customs broker > Add: Type Receiver, Name and Contact QA Test Recipient, same address, city, post code and phone as Ship to > Use for this shipment 10. Items: Description Cotton T-shirt, HS code 61091000, Origin US, Qty 2, Unit value 20.00, Wt 0.5 11. Click Validate shipment, then Generate label 12. Repeat with FedEx Envelope (International Economy and Priority), FedEx 25kg Box, and with carrier UPS, Worldwide Saver and Worldwide Express, UPS 10KG Box (10 lb) and UPS 25KG Box (20 lb) | J4: FedEx: #934063 (IE Envelope), #934068 (IP 10kg), #934069 (IP 25kg), #934070 (IP Envelope). UPS: #934079, #934080 (Saver 10KG/25KG), #934091, #934092 (Express 10KG/25KG) | K4: The form allows only one box for these single-piece packagings, or the check blocks Generate with a message about the box count. | L4: FedEx check: ready to ship with one item to review, the note 'Multi-package validate: FedEx only supports single-piece pre-flight; box 1 validated, boxes 2–2 verified at label create'. Label: 'The package count for this shipment exceeds limit.' UPS check: ready to ship with one item to review (the UPS rate call returned HTTP 400 with the same message as below), Carrier check passed and Generate enabled; label: 'The requested service is not valid for shipments with the requested packaging.', which is misleading because the same service and packaging generate as one box (#934075-#934078, #934093, #934094, #934103, #934104 and every UK/Mexico 1-box order). 8 of 8 two-box attempts failed. | M4: API errorDetails: 'FEDEX createShipment HTTP 400 ... The package count for this shipment exceeds limit.' (#934063, #934068-#934070); 'UPS createShipment HTTP 400 ... The requested service is not valid for shipments with the requested packaging.' (#934079, #934080, #934091, #934092) | N4: /orders/new | O4: Always (8 of 8 two-box attempts; 0 failures as one box) | P4: BUG-003.jpg, BUG-003-2.jpg, BUG-003-3.jpg, BUG-003-4.jpg, BUG-003-5.png, BUG-003-6.png | R4: admin (ADMIN) | T4: 2026-10-11 | U4: R1 | V4: S001 | X4: Closed | Y4: 2026-10-12 R3: fixed - Single-piece packagings now refuse extra boxes. With FedEx Envelope, both 'Add another box' and 'Add N boxes like the last' are disabled=true with the tooltip 'FedEx Envelope ships at most 1 box per label. If you need to ship more than one box, create each one as a separate shipment.'; UPS 10KG Box gives the same guard. With an extra box already on the form, switching to UPS 10KG Box raises an inline warning naming the consequence: 'UPS 10KG Box ships at most 1 box per label - the carrier will reject this 2-box shipment. Remove the extra boxes or pick a larger packaging.' The label is no longer bought and then rejected. Note the new BUG-053: in exactly that state the Validate button goes silent. 2026-10-13 R4 (build local dev, 2026-10-13): fixed - Re-walked on UPS. With UPS 10KG Box selected, 'Add another box' and 'Add N boxes like the last' are both disabled=true with the tooltip 'UPS 10KG Box ships at most 1 box per label. To ship multiple boxes, create each one as a separate shipment.', and an existing extra box raises the inline warning 'UPS 10KG Box ships at most 1 box per label - the carrier will reject this 2-box shipment. Remove the extra boxes or pick a larger packaging.' 2026-10-13 R5 (build local dev, 2026-10-13 (rebuilt after R4; frontend modules dated 13:12 IST)): fixed - Regression check passed on FedEx: with FedEx International Priority and Packaging 'FedEx 10kg Box', both 'Add another box' and 'Add N boxes like the last' are disabled with the tooltip 'FedEx 10kg Box ships at most 1 box per label. If you need to ship more than one box, create each one as a separate shipment.' (UPS checked separately under BUG-053). UPS checked too: with UPS 10KG Box selected and two boxes already on the form, 'Add another box' and 'Add N boxes like the last' are disabled with 'UPS 10KG Box ships at most 1 box per label. To ship multiple boxes, create each one as a separate shipment.', and the inline warning names the 2-box conflict. | Z4: New
A5: BUG-004 | B5: Medium | C5: Functional | D5: Orders | E5: New order | F5: New order form (international) | G5: Shipment check panel | H5: Shipment check (FedEx International Priority): '1 issue to fix: FEDEX did not quote FedEx International Priority' although IP is in the quoted list; Generate stays enabled | I5: 1. Open Orders and click + New shipment (/orders/new) 2. Client: MKL246 (ship from 3PL-EAST, the client default) 3. Carrier: FedEx 4. Ship to: Full name QA Test Recipient, Company QA Test Co, Address line 1 Av Paseo de la Reforma 222, Country Mexico (MX), Phone 5552081234, State / region CMX, City Ciudad de Mexico, Postal code 06600 5. Service level: FedEx International Priority 6. Packaging THB-PACKAGE, Weight 5 (one box) 7. Customs: Reason of export Sale, Label type PDF, Incoterms DAP 8. Importer of record & customs broker > Add: Type Receiver, Name and Contact QA Test Recipient, same address, city, post code and phone as Ship to > Use for this shipment 9. Items: Description Cotton T-shirt, HS code 61091000, Origin US, Qty 2, Unit value 20.00, Wt 0.5 10. Click Validate shipment | J5: Retest 2026-10-12, reference QA-1012-EVID-MX-FX-IP (validated only, not saved), and the same on a UK tube shipment. During the run: every International Priority shipment whose FedEx rate call succeeded, e.g. #934072, #934074, #934118, #934122, #934157, #934161-#934163 | K5: No issue when the selected service is in the quoted list. A check that says an issue must be fixed before the label can be bought should also keep Generate disabled. | L5: Check header '1 issue to fix before the label can be bought · 1 to review'; Account, service & price '1 to fix': 'FEDEX did not quote FedEx International Priority for this lane — the label may be refused. Quoted instead: FedEx International Connect Plus — USD 159.18; FedEx International Economy® — USD 174.95; FedEx International Priority® — USD 218.58; FedEx International Priority® Express — USD 229.64; FedEx International First® — USD 271.64.' The same sentence is listed twice (as to fix and to review) and again in the price box. Generate label stays enabled and the labels generate. Seen for Canada, UK and Mexico; retested 2026-10-12 for Mexico and UK. | M5: The quoted list contains 'FedEx International Priority®' (with the registered mark), which may be why the match on the service name fails. No console capture. | N5: /orders/new | O5: Always when the FedEx rate call succeeds | P5: BUG-004.jpg, BUG-004-2.jpg, BUG-004-3.jpg, BUG-004-4.jpg, BUG-004-5.png, BUG-004-6.jpg, BUG-004-7.jpg, BUG-004-8.jpg, BUG-004-9.jpg, BUG-004-10.png, BUG-004-11.png | R5: admin (ADMIN) | T5: 2026-10-11 | U5: R1 | V5: S001 | X5: Closed | Y5: 2026-10-12 R3: fixed - FedEx International Priority to Mexico (MKL246, THB-PACKAGE 5 lb, importer Receiver) now returns 'All checks passed - ready to generate the label' with Account, service & price Passed and the detail 'PRICE & DELIVERY - FEDEX INTERNATIONAL PRIORITY(R) Price USD 218.58 Billed weight 5 lb > Other FEDEX services on this lane (4)'. The contradictory 'FEDEX did not quote FedEx International Priority' issue is gone and the selected service is matched to the quote. 2026-10-13 R4 (build local dev, 2026-10-13): fixed - FedEx International Priority to Ciudad de Mexico now matches the selected service to the quote: Account, service & price shows 'PRICE & DELIVERY - FEDEX INTERNATIONAL PRIORITY / Billed weight 4 lb' and the contradictory 'FEDEX did not quote FedEx International Priority' issue is gone. The only note on this run was a genuine sandbox outage - 'No price: FEDEX rate call failed - HTTP 503 The service is currently unavailable' - which is the carrier being down, not the bug. 2026-10-13 R5 (build local dev, 2026-10-13 (rebuilt after R4; frontend modules dated 13:12 IST)): fixed - Regression check passed once the FedEx sandbox answered (the first two validations got 'HTTP 503'). FedEx International Priority, MKL246 to Av Paseo de la Reforma 222, Ciudad de Mexico CMX 06600, THB-PACKAGE 5 lb: the check reads 'All checks passed - ready to generate the label' with Account, service & price Passed; the quote is QUOTED 'FedEx International Priority(R)' USD 218.58, with Connect Plus 159.18, Economy 174.95, Priority Express 229.64 and First 271.64 listed as alternatives. The contradictory 'FEDEX did not quote FedEx International Priority' issue does not appear. | Z5: New
A6: BUG-005 | B6: Medium | C6: Usability | D6: Orders | E6: New order | F6: New order form (international) | G6: FTR exemption (UK, Mexico) | H6: New shipment (FedEx to Canada): no FTR exemption field; with Export declaration ref empty FedEx rejects 'FTR Exemption or AES Citation ... not valid for EEI' | I6: 1. Open Orders and click + New shipment (/orders/new) 2. Client: MKL246 (ship from 3PL-EAST, the client default) 3. Carrier: FedEx 4. Ship to: Full name QA Test Recipient, Company QA Test Co, Address line 1 290 Bremner Blvd, Country Canada (CA), Phone 4165550100, State / region ON, City Toronto, Postal code M5V 3L9 5. Service level: FedEx International Economy 6. Packaging FedEx Pak, Weight 2 (one box) 7. Customs: Reason of export Sale; note there is no FTR exemption or AES ITN field for Canada; leave Export declaration ref empty; Label type PDF; Label size Paper 4x6; Incoterms DAP 8. Importer of record & customs broker > Add: Type Receiver, Name and Contact QA Test Recipient, same address, city, post code and phone as Ship to > Use for this shipment 9. Items: Description Cotton T-shirt, HS code 61091000, Origin US, Qty 2, Unit value 20.00, Wt 0.5 10. Click Validate shipment | J6: Retest 2026-10-12, reference QA-1012-EVID-CA-FX-IE (validated only, not saved). During the run all Canada FedEx orders (#934063-#934078) needed the workaround | K6: Canada gets the same FTR exemption dropdown as the UK and Mexico forms (which already list 'NOEEI §30.36 — export to Canada'), or a valid default, so a low-value shipment passes without typing a citation. | L6: Carrier check '1 to fix': 'FedEx rejected the shipment: The FTR Exemption or AES Citation you provided is not valid for EEI.' Generate label stays disabled, while 'Customs & dangerous goods' shows Passed. Typing 'NO EEI 30.36' into Export declaration ref makes the check pass. | M6: Canada form selects: Reason of export, Currency, Label type, Label size, Pickup type, Incoterms, Duties paid by - no FTR exemption (UK and Mexico forms have it). | N6: /orders/new | O6: Always | P6: BUG-005.jpg, BUG-005-2.jpg, BUG-005-3.png, BUG-005-4.png | R6: admin (ADMIN) | T6: 2026-10-11 | U6: R1 | V6: S001 | X6: Closed | Y6: 2026-10-12 R3: fixed - The Canada form now carries an FTR EXEMPTION dropdown and an AES ITN (CENSUS) field next to Reason of export. The dropdown offers '-- None (using AES) --', 'NOEEI 30.37(a) - value under $2,500 USD', 'NOEEI 30.37(h) - tools of trade / temporary export' and 'NOEEI 30.36 - export to Canada'. With Export declaration ref left empty and the exemption left at None, Validate shipment returned all five checks Passed, Carrier check included - the 'FTR Exemption or AES Citation you provided is not valid for EEI' refusal is gone. 2026-10-13 R4 (build local dev, 2026-10-13): fixed - The FTR EXEMPTION dropdown and AES ITN (CENSUS) field are present on the Canada form. A Canada shipment validated with the exemption left at '-- None (using AES) --' and Export declaration ref empty returned all five checks Passed, Carrier check included. 2026-10-13 R5 (build local dev, 2026-10-13 (rebuilt after R4; frontend modules dated 13:12 IST)): fixed - Fixed as the bug asked: the Canada form now has the FTR EXEMPTION dropdown (None (using AES), NOEEI 30.37(a), NOEEI 30.37(h), NOEEI 30.36 - export to Canada) and an AES ITN (CENSUS) field. With the original steps (FedEx International Economy, FedEx Pak 2 lb, Toronto ON M5V 3L9, Export declaration ref empty) and 'NOEEI 30.36 - export to Canada' picked, the check returns 'Local + FEDEX checks passed. Ready to generate the label.' with no citation typed. Unlike R4, though, leaving the exemption at its default '-- None (using AES) --' now gets 'FedEx rejected the shipment: The FTR Exemption or AES Citation you provided is not valid for EEI.' again (2 of 2 validations, IE/Pak and IP/10kg Box), while Customs & dangerous goods says Passed - logged separately as a new validation finding. | Z6: New
A7: BUG-006 | B7: Medium | C7: Functional | D7: Orders | E7: New order | F7: New order form (international) | G7: Add N boxes like the last | H7: New shipment: 'Add N boxes like the last' copies the weight but leaves Length / Width / Height empty for a carrier box | I7: 1. Open Orders and click + New shipment (/orders/new) 2. Client: MKL246 (ship from 3PL-EAST, the client default) 3. Carrier: UPS 4. Ship to country Mexico 5. Service level: UPS Worldwide Saver 6. Packaging UPS Large Express Box, Weight 4 7. Set the box count next to 'boxes like the last' to 1 8. Click 'boxes like the last' (tooltip: 'Adds boxes copying the last box's weight and dimensions (box 1's when there is no extra box yet)') | J7: Seen on MX-UP-WWS-LBOX (#934168) during the run; retested 2026-10-12 (form not saved) | K7: Box 2 gets weight 4 lb and the box's dimensions 18 x 13 x 3 in, as the tooltip says. | L7: Box 2 shows Weight 4 and empty L, W and H fields. Apply box 1 to all fills them (18 x 13 x 3). | M7: Box card after the click: 'BOX 2 ... Weight (lb) 4, L (in) [empty], W (in) [empty], H (in) [empty]' | N7: /orders/new | O7: Always (2 of 2) | P7: BUG-006.jpg, BUG-006-2.jpg, BUG-006-3.jpg | R7: admin (ADMIN) | T7: 2026-10-11 | U7: R1 | V7: S001 | X7: Closed | Y7: 2026-10-12 R3: fixed - Retested on the exact original repro: UPS Large Express Box, weight 4, 'Add 1 boxes like the last'. Box 2 now reads 'BOX 2 4 lb - 18x13x3 in' - the dimensions are copied as well as the weight, and the extra box is shown as a compact summary with Duplicate / Edit / delete. Same result with a Custom package carrying 18x13x3. One gap remains: for THB-PACKAGE, which has no dimension fields of its own, box 2 still opens with empty L, W and H. 2026-10-13 R4 (build local dev, 2026-10-13): fixed - Re-walked on the original repro: UPS Large Express Box, weight 4, 'Add 1 boxes like the last' gives 'BOX 2 4 lb - 18x13x3 in'. Weight and dimensions are both copied. 2026-10-13 R5 (build local dev, 2026-10-13 (rebuilt after R4; frontend modules dated 13:12 IST)): fixed - Regression check passed: UPS Large Express Box, weight 4, 'Add 1 boxes like the last' gives 'BOX 2 4 lb - 18x13x3 in' - weight and dimensions both copied (checked on the Canada lane). | Z7: New
A8: BUG-007 | B8: Medium | C8: Functional | D8: Orders | E8: Label | F8: Label documents | G8: Label preview | H8: Label documents #934118: label stored as a FedEx document link instead of the PDF; each label request takes 3-4 s and the page shows 'Loading label document...' for about 8 s | I8: 1. Open /label/934118 (Orders > order #934118 > View label) 2. Watch the label area and the Download / Print buttons 3. Compare with /label/934119 (same carrier, service and lane) | J8: Order #934118 (QA-1011-R13-GB-FX-IP-10KG-1B), FedEx International Priority to the UK | K8: The label is stored like the other 114 labels and the page shows it within a second. | L8: 'Loading label document...' with Download PDF, Download .zpl, Copy ZPL and Print Label disabled until about 12 s after opening the page (about 3 s for #934119), then the label renders. The order's labelDetails.labelFilePath holds 'https://wwwtest.fedex.com/document/v1/cache/retrieve/SH...' (124 characters) while the other 114 generated orders hold the base64 PDF. Whether that FedEx link expires was not verified. | M8: GET /api/v1/orders/934118/label 3.6-4.3 s, GET /api/v1/orders/934118/label/pdf 3.4 s; for #934119: 55-109 ms and 21 ms (browser resource timing, 2026-10-12). | N8: /label/934118 | O8: Always for #934118 (1 of 115 labels) | P8: BUG-007.jpg, BUG-007-R7.jpg | R8: admin (ADMIN) | T8: 2026-10-11 | U8: R1 | V8: S003 | W8: API > Orders > Order detail (GET /api/v1/orders/{id}) | X8: Reopened | Y8: 2026-10-12 R3: still-failing - Unchanged. /label/934118 shows 'Loading label document...' with Download PDF, Download .zpl, Copy ZPL and Print Label disabled for about 10-12 seconds (about 3 seconds for /label/934119 on the same carrier and lane). GET /api/v1/orders/934118 still returns labelDetails.labelFilePath as a 124-character 'https://wwwtest.fedex.com/document/v1/cache/retrieve/SH...' link while the other generated orders hold the base64 PDF (934119: 18,376 characters; 934190: 133,684). The rendered document is also still the one-page FedEx text placeholder rather than the 4-page SANDBOX label the other orders show. 2026-10-13 R4 (build local dev, 2026-10-13): still-failing - Unchanged on the 2026-10-13 build. GET /api/v1/orders/934118 still returns labelDetails.labelFilePath as a 124-character https://wwwtest.fedex.com/document/v1/cache/retrieve/... link, while every other generated order holds the base64 PDF (934119: 18,376 characters; 934172: 59,768; 934190: 133,684). The label page for 934118 still sits on 'Loading label document...' with the download and print buttons disabled for roughly ten seconds against about three for the others. 2026-10-13 R5 (build local dev, 2026-10-13 (rebuilt after R4; frontend modules dated 13:12 IST)): still-failing - New labels are fine; the order in the bug is not, and the guard itself could not be exercised. A new FedEx International Priority label to the UK (order #934193, 2 x FedEx Tube, reference QA-1013-R5-GB-FX-IP-TUBE-2B, generated with Manoj's permission) is stored as a PDF - labelDetails.labelFilePath is an 18,308-character base64 string starting %PDF - and /label/934193 renders at once (GET /label 184-248 ms, /label/pdf 36 ms). But the original fault hit 1 label in 115, so one clean label does not show that the new URL-only guard works, and FedEx cannot be made to return a link-only label on demand. Order #934118 itself is unchanged: GET /api/v1/orders/934118 still returns a 124-character https://wwwtest.fedex.com/document/... link and GET /label takes 2.3 s against 63 ms for #934119. The developers say an admin label-backfill endpoint can repair it; that endpoint is not in the interface, so it was not run. Please run it for #934118 and the order can be re-checked. 2026-10-14 R6 (build local dev, 2026-10-14 (order-form modules reloaded 13:17 IST)): still-failing - R6: unchanged - the backfill has not been run. /label/934118 still opens on 'Loading label document...' with Download PDF, Download .zpl, Copy ZPL and Print Label disabled; GET /api/v1/orders/934118 takes about 4.0 s and its labelDetails.labelFilePath is still the 124-character https://wwwtest.fedex.com/document/... link; GET /label 3.9 s and the two preview.png requests 4.5 s and 6.0 s. 2026-10-16 R7 (build local dev, 2026-10-16): still-failing - unchanged - the backfill the developers describe has not been run. /label/934118 opens on 'Loading label document...' with Download PDF, Download .zpl, Copy ZPL and Print Label disabled, the header enables at about 6 s and the label renders at about 12 s (screenshots at 1, 6 and 12 s); /label/934119 renders within 2 s. GET /api/v1/orders/934118 still returns labelDetails.labelFilePath as the 124-character https://wwwtest.fedex.com/document/... link while #934172, #934190 and #934192 hold base64 PDFs (59,768 to 133,684 characters). New labels bought in this run (#934195, #934196) are stored as PDF and open at once. Needs the admin label-backfill run for #934118, then a recheck. | Z8: Deferred | AB8: Deferred to next round: Needs backfill endpoint invocation for #934118; no new code. | AC8: 2026-10-13
A9: BUG-008 | B9: Low | C9: Usability | D9: Orders | E9: New order | F9: New order form (international) | G9: State / region (UK, Mexico) | H9: New shipment (ship to Mexico): State / region is required but has no * marker, a US placeholder 'NY', and accepts only ISO codes as free text | I9: 1. Open Orders and click + New shipment (/orders/new) 2. Client: MKL246 (ship from 3PL-EAST, the client default) 3. Carrier: FedEx 4. Ship to country Mexico; fill name, address, city Ciudad de Mexico, postal code 06600; leave State / region empty 5. Complete the rest of the form and click Validate shipment 6. Enter DF in State / region and click Validate shipment again | J9: Retest 2026-10-12 (QA-1012-EVID-MX-FX-IP, not saved); during the run every Mexico order needed CMX | K9: Required fields carry the * marker used elsewhere on the form, and Mexico offers a state dropdown like Canada's province list, so a valid code is picked rather than guessed. | L9: The label 'STATE / REGION' has no * (City * and Postal code * do), and the placeholder is 'NY'. Empty: toast '1 field needs attention — Ship to state: state / region is required' and the field turns red. 'DF' is accepted by the field and only rejected by the check; 'CMX' works. The run notes recorded Validate doing nothing visible; on retest the toast appeared, so that part is not reported. | N9: /orders/new | O9: Always | P9: BUG-008.jpg, BUG-008-2.jpg, BUG-008-3.png, BUG-008-4.jpg, BUG-008-5.jpg, BUG-008-6.png, BUG-008-7.png | R9: admin (ADMIN) | T9: 2026-10-11 | U9: R1 | V9: S001 | X9: Closed | Y9: 2026-10-12 R3: still-failing - Two of the three parts are fixed. The label now reads 'STATE / REGION *' with the red asterisk the other required fields carry, and the placeholder for Mexico is now 'CMX', a real Mexican state code, not the US 'NY'. What remains: the field is still a free-text input for Mexico, not a dropdown of Mexican states the way Canada gets a province list and the US gets a state list - and it silently accepts a value carried over from another country (switching Canada to Mexico left 'ON' in the box, which only the carrier check later rejects). 2026-10-13 R4 (build local dev, 2026-10-13): fixed - Mexico now gets a proper state list. With the country set to Mexico, State / region becomes a 32-entry dropdown (AGU - Aguascalientes, BCN - Baja California, BCS - Baja California Sur, CAM - Campeche, CHP - Chiapas and the rest) with the required asterisk on the label. The US placeholder 'NY' and the free-typed guessing are both gone, and a value carried over from another country can no longer survive the switch. 2026-10-13 R5 (build local dev, 2026-10-13 (rebuilt after R4; frontend modules dated 13:12 IST)): fixed - Regression check passed: with Ship to country Mexico, State / region is a dropdown of 32 states (AGU - Aguascalientes ... CMX - Ciudad de Mexico ...) labelled 'STATE / REGION *'; the postal code placeholder reads 'e.g. 01000'. Changing the state does not clear City or Postal code. | Z9: New
A10: BUG-009 | B10: Low | C10: Content | D10: Orders | E10: New order | F10: New order form (international) | G10: Shipment check panel | H10: Shipment check (Mexico): state message says 'Use the 2-letter code (e.g. CMX, JAL, NLE)' but every example is three letters | I10: 1. Open Orders and click + New shipment (/orders/new) 2. Client: MKL246 (ship from 3PL-EAST, the client default) 3. Carrier: FedEx 4. Ship to country Mexico with State / region DF 5. Complete the form and click Validate shipment | J10: QA-1012-EVID-MX-FX-IP (validated only) | K10: The message asks for the 3-letter state code (CMX, JAL, NLE). | L10: Addresses '1 to fix': 'State/province "DF" isn't a valid MX code. Use the 2-letter code (e.g. CMX, JAL, NLE), not the full name.' | N10: /orders/new | O10: Always | P10: BUG-009.jpg, BUG-009-2.jpg, BUG-009-3.png | R10: admin (ADMIN) | T10: 2026-10-12 | U10: R1 | V10: S001 | X10: Closed | Y10: 2026-10-12 R3: fixed - The check message now reads: 'State/province "DF" isn't a valid MX code. Use the official code (e.g. CMX, JAL, NLE), not the full name.' The wrong '2-letter code' wording is gone, so the instruction and the examples agree. 2026-10-13 R4 (build local dev, 2026-10-13): fixed - Unreachable by design now. Because Mexico's State / region is a dropdown of official codes, an invalid value such as DF cannot be typed, so the message 'Use the 2-letter code (e.g. CMX, JAL, NLE)' no longer appears. The wording was already corrected to 'Use the official code' on 2026-10-12. 2026-10-13 R5 (build local dev, 2026-10-13 (rebuilt after R4; frontend modules dated 13:12 IST)): fixed - Regression check passed: the message cannot be reached any more because Mexico's State / region only offers official codes from a dropdown, so an invalid value such as DF cannot be entered. | Z10: New
A11: BUG-010 | B11: Low | C11: Content | D11: Orders | E11: New order | F11: New order form (international) | G11: Importer of record & customs broker: Add | H11: New shipment (Mexico): Importer section shows the badge 'RESOLVED FOR MX' next to the warning 'No importer/broker profile covers MX for MKL246' | I11: 1. Open Orders and click + New shipment (/orders/new) 2. Client: MKL246 (ship from 3PL-EAST, the client default) 3. Carrier: USPS (also seen with FedEx) 4. Ship to country Mexico 5. Look at the Importer of record & customs broker section before adding an override | J11: Seen 2026-10-12 (forms not saved) | K11: The badge and the message agree: no profile means no 'resolved' badge (the FedEx ship-to card also shows 'Importer/broker resolved for MX'). | L11: Badge 'RESOLVED FOR MX' and, below it, 'No importer/broker profile covers MX for MKL246. Click Add to enter importer/broker for this shipment only'. | N11: /orders/new | O11: Always | P11: BUG-010.jpg, BUG-010-2.jpg, BUG-010-3.png | R11: admin (ADMIN) | T11: 2026-10-12 | U11: R1 | V11: S001 | X11: Closed | Y11: 2026-10-12 R3: fixed - For a Mexico shipment with no importer profile, the badge now reads 'NOT CONFIGURED' in grey next to the message 'No importer/broker profile covers MX for MKL246. Click Add to enter importer/broker for this shipment only (the client's saved profile is not changed).' The contradictory 'RESOLVED FOR MX' badge is gone. Once an override is entered the badge becomes 'OVERRIDDEN - THIS SHIPMENT' and the Ship to card shows the green 'Importer/broker resolved for CA' chip - both now only when something really is resolved. 2026-10-13 R4 (build local dev, 2026-10-13): fixed - On a Canada shipment with no importer profile the badge reads 'NOT CONFIGURED' beside 'No importer/broker profile covers CA for MKL246...', and on a UK shipment the Ship to card reads the amber 'No importer/broker profile for GB - set one up'. The badge only says resolved once an override is actually applied. 2026-10-13 R5 (build local dev, 2026-10-13 (rebuilt after R4; frontend modules dated 13:12 IST)): fixed - Regression check passed on the Mexico lane: before an override the Importer section reads 'NOT CONFIGURED' beside 'No importer/broker profile covers MX for MKL246. Click Add to enter importer/broker for this shipment only...', and after Receiver - DAP is applied it reads 'OVERRIDDEN - THIS SHIPMENT'. No 'resolved' badge appears without a profile. | Z11: New
A12: BUG-011 | B12: Low | C12: Usability | D12: Orders | E12: New order | F12: New order form (international) | G12: Item HS code and lookup | H12: New shipment (Canada): HS code lookup suggests the 6-digit 610910, which the form then rejects as too short | I12: 1. Open Orders and click + New shipment (/orders/new) 2. Client: MKL246 (ship from 3PL-EAST, the client default) 3. Carrier: FedEx 4. Ship to country Canada 5. Items: Description Cotton T-shirt; take the HS code the lookup suggests | J12: First Canada shipment of the run (2026-10-11) | K12: The lookup offers a code long enough for the destination (8+ digits for Canada). | L12: Lookup gives 610910; inline error 'CA needs at least an 8-digit HS code (you entered 6)'. 61091000 typed by hand is accepted. | N12: /orders/new | O12: Seen once (not retested) | P12: BUG-011.png | R12: admin (ADMIN) | T12: 2026-10-11 | U12: R1 | V12: S001 | X12: Closed | Y12: 2026-10-12 R3: fixed - Typing 't-shirt' into HS code on a Canada shipment still lists 610910 and 610990, but picking 610910 now inserts 61091000 into the field - the lookup pads the code to the destination's required length. No inline error, and the Customs check passed. The hint under the field reads 'HS code should be 6-10 digits (e.g. 6104.62.20). Dots/spaces are OK; letters are not.' 2026-10-13 R4 (build local dev, 2026-10-13): fixed - Typing 't-shirt' into HS code on a Canada shipment lists 610910 and 610990; picking 610910 inserts 61091000 into the field. The code is padded to the destination's required length and the Customs check passes. 2026-10-13 R5 (build local dev, 2026-10-13 (rebuilt after R4; frontend modules dated 13:12 IST)): fixed - Regression check passed: typing t-shirt into HS code on the Canada shipment lists 610910 and 610990, and picking 610910 fills the field with 61091000, the 8 digits Canada needs. The suggestion list itself is too narrow to read - logged separately. | Z12: New
A13: BUG-012 | B13: Low | C13: Content | D13: Orders | E13: New order | F13: New order form (international) | G13: Ship-from address (from client profile) | H13: Client MKL246 ship-from address: Address line 1 '8191 Logistics Dr,' ends with a stray comma | I13: 1. Open Orders and click + New shipment (/orders/new) 2. Client: MKL246 (ship from 3PL-EAST, the client default) 3. Look at Ship from > Address line 1 | J13: MKL246 / 3PL-EAST ship-from profile | K13: Address line 1 without trailing punctuation; it is printed on labels and sent to the carriers. | L13: '8191 Logistics Dr,' | N13: /orders/new | O13: Always | P13: BUG-012.jpg | R13: admin (ADMIN) | T13: 2026-10-11 | U13: R1 | V13: S001 | X13: Closed | Y13: 2026-10-12 R3: still-failing - Client MKL246's ship-from Address line 1 still reads '8191 Logistics Dr,' with the trailing comma, on the New shipment form at /orders/new. 2026-10-13 R4 (build local dev, 2026-10-13): still-failing - Unchanged. Picking client MKL246 on the New shipment form still fills Ship from Address line 1 as '8191 Logistics Dr,' with the trailing comma. 2026-10-13 R5 (build local dev, 2026-10-13 (rebuilt after R4; frontend modules dated 13:12 IST)): fixed - Picking client MKL246 on /orders/new now fills Ship from Address line 1 as '8191 Logistics Dr' with no trailing comma (Ship from 3PL-EAST - Central Warehouse, Zeeland MI 49464). The validate request sends addressLine1 '8191 Logistics Dr' to the server as well. | Z13: Fixed | AB13: Fixed on dev (a0238990): V149 strips trailing comma from warehouse.line1/line2 (3PL-EAST was leaking the string onto labels; V147 only touched clients table). | AC13: 2026-10-13
A14: BUG-013 | B14: Low | C14: Usability | D14: Orders | E14: New order | F14: New order form (international) | G14: Add item | H14: New shipment > Items: 'Add item' inserts the new blank line above the existing one | I14: 1. Open Orders and click + New shipment (/orders/new) 2. Client: MKL246 (ship from 3PL-EAST, the client default) 3. Carrier: USPS; ship to country Mexico 4. Fill item line 1: Cotton T-shirt, 61091000, US, 1, 20.00, 0.5 5. Click + Add item | J14: Seen during the run (USPS split shipments) and on retest 2026-10-12 | K14: The new line is added below the existing line, or focus moves into the new line. | L14: A blank line appears as row 1 and the filled line moves to row 2, so the next values typed into the top row go into the new line. | N14: /orders/new | O14: Always | P14: BUG-013.jpg, BUG-013-2.jpg, BUG-013-3.jpg, BUG-013-4.jpg, BUG-013-5.png | R14: admin (ADMIN) | T14: 2026-10-11 | U14: R1 | V14: S001 | X14: Closed | Y14: 2026-10-12 R3: fixed - With item line 1 filled (Cotton T-shirt, 61091000, US, 2, 20.00, 0.5), clicking + Add item now appends the blank line as row 2 and leaves the filled line as row 1. 2026-10-13 R4 (build local dev, 2026-10-13): fixed - With item line 1 filled, + Add item appends the blank line below it as row 2; the filled line stays at row 1. 2026-10-13 R5 (build local dev, 2026-10-13 (rebuilt after R4; frontend modules dated 13:12 IST)): fixed - Regression check passed: with item line 1 filled (Cotton T-shirt, 61091000, US, 2, 20.00, 0.5), + Add item appends the blank line as row 2 and the filled line stays in row 1. | Z14: New
A15: BUG-014 | B15: Low | C15: UI | D15: Orders | E15: New order | F15: New order form (international) | G15: Boxes: Spread across 2 boxes | H15: New shipment: the 'Lines spread across 2 boxes' toast covers the Validate shipment and Generate label buttons | I15: 1. Open Orders and click + New shipment (/orders/new) 2. Client: MKL246 (ship from 3PL-EAST, the client default) 3. Carrier: USPS; ship to country Mexico 4. Add another box (2 boxes) 5. Two item lines (Add item) 6. Click Boxes > Spread across 2 boxes | J15: Seen during the run and on retest 2026-10-12 | K15: Confirmation toasts do not sit over the footer's main buttons. | L15: Toast 'Done — Lines spread across 2 boxes in order — adjust any line's Pkg # if needed.' covers Validate shipment and Generate label at the bottom right; during the run the Validate click did not go through until the toast was closed. | N15: /orders/new | O15: Always | P15: BUG-014.jpg, BUG-014-2.jpg, BUG-014-3.jpg | R15: admin (ADMIN) | T15: 2026-10-11 | U15: R1 | V15: S001 | X15: Closed | Y15: 2026-10-12 R3: fixed - With 2 boxes and 2 item lines, Boxes > 'Spread across 2 boxes' shows the toast 'Done - Lines spread across 2 boxes in order - adjust any line's Pkg # if needed.' clear of the footer: Validate shipment and Generate label stay fully visible and clickable while it is on screen. The lines were correctly assigned Pkg # 1 and 2. 2026-10-13 R4 (build local dev, 2026-10-13): fixed - Boxes > 'Spread across 2 boxes' shows 'Done - Lines spread across 2 boxes in order - adjust any line's Pkg # if needed.' clear of the footer, with Validate shipment and Generate label both fully visible and clickable. 2026-10-13 R5 (build local dev, 2026-10-13 (rebuilt after R4; frontend modules dated 13:12 IST)): fixed - Regression check passed: Boxes > 'Spread across 2 boxes' shows the toast 'Done - Lines spread across 2 boxes in order - adjust any line's Pkg # if needed.' at the right, above the footer, with Validate shipment and Generate label clear and clickable; the toast dismisses itself after a few seconds. While it is up it sits over the right end of the minimised Shipment check bar (its 'Check again' and 'Show details' buttons), which is cosmetic because the footer's Validate shipment does the same job. | Z15: New
A16: BUG-015 | B16: Low | C16: Functional | D16: Orders | E16: Label | F16: Label documents | G16: Label preview | H16: Label documents: every page load gets HTTP 503 from HEAD /label/preview.png before falling back to the PDF | I16: 1. Open /label/934119 (or any generated order's label page) 2. Read the network requests | J16: Orders #934118, #934119, #934190 (2026-10-12) | K16: The preview request succeeds, or the page asks for the PDF directly; no 5xx on a normal page load. | L16: HEAD /api/v1/orders/{id}/label/preview.png?pkg=1 -> 503, twice per load, then GET /label/pdf -> 200 and the label shows. Each /label request is also sent twice (possibly React StrictMode in the dev build). | M16: HEAD /api/v1/orders/934119/label/preview.png?pkg=1 -> 503 (x2); GET /api/v1/orders/934119/label -> 200 (x2); GET /api/v1/orders/934119/label/pdf -> 200 | N16: /label/{orderNo} | O16: Always (3 of 3 pages) | P16: Not captured | R16: admin (ADMIN) | T16: 2026-10-12 | U16: R1 | V16: S003 | X16: Closed | Y16: 2026-10-12 R3: still-failing - Unchanged. On /label/934119 and /label/934118 the page still sends HEAD /api/v1/orders/{id}/label/preview.png?pkg=1 -> 503 twice per load before falling back to GET /label/pdf -> 200, and GET /api/v1/orders/{id}/label is still sent twice. 2026-10-13 R4 (build local dev, 2026-10-13): still-failing - Unchanged. /label/934119 still sends HEAD /api/v1/orders/934119/label/preview.png?pkg=1 -> 503 twice per page load before falling back to GET /label/pdf -> 200, and GET /api/v1/orders/934119/label is still sent twice. 2026-10-13 R5 (build local dev, 2026-10-13 (rebuilt after R4; frontend modules dated 13:12 IST)): fixed - No 5xx any more. Opening the label page of the new order #934192 sends HEAD /api/v1/orders/934192/label/preview.png?pkg=1 -> 404 (twice, about 120 ms each) and then GET /label/pdf?pkg=1 -> 200 in 50 ms, and the label renders; no console error. The page still probes for a PNG preview that never exists for this carrier, now answered with a clean 404 instead of 503, and GET /label is still sent twice per load (React StrictMode in dev). | Z16: Fixed | AB16: Fixed on dev (d52bc26f): HEAD short-circuit shipped 2026-10-12; verified via curl: HEAD now returns 404 not 503. QA R4 stale backend. | AC16: 2026-10-13
A17: BUG-016 | B17: Low | C17: Content | D17: Orders | E17: New order | F17: New order form (international) | G17: Validate shipment | H17: Validate shipment: a server failure shows the raw toast 'Something went wrong HTTP error! status: 502' | I17: 1. Open Orders and click + New shipment (/orders/new) 2. Client: MKL246 (ship from 3PL-EAST, the client default) 3. Carrier: FedEx 4. Ship to: Full name QA Test Recipient, Company QA Test Co, Address line 1 Av Paseo de la Reforma 222, Country Mexico (MX), Phone 5552081234, State / region CMX, City Ciudad de Mexico, Postal code 06600 5. Service level: FedEx International Economy; Packaging FedEx Pak; 2 boxes 6. Fill customs, importer and items as for the other Mexico FedEx orders 7. Click Validate shipment | J17: First Validate of MX-FX-IE-PAK (order later created as #934153) | K17: A plain message that the check could not run and to try again; no HTTP wording. | L17: Toast 'Something went wrong HTTP error! status: 502'; no check panel and no order. Clicking Validate again worked. | N17: /orders/new | O17: 1 of about 40 FedEx validations | P17: Not captured | R17: admin (ADMIN) | T17: 2026-10-11 | U17: R1 | V17: S001 | X17: Closed | Y17: 2026-10-12 R3: cannot-retest - The 502 was a one-off server failure and could not be provoked again. Validate shipment was run about a dozen times during this retest across FedEx, UPS and USPS on the Canada, Mexico and UK lanes and returned 200 every time, so the raw 'Something went wrong HTTP error! status: 502' toast never reappeared. The wording of the error path is therefore unverified; note that other raw text is still shown to the user - the USPS no-price message prints the carrier's JSON ('error_reference_id ... error_code 4522242 ...') in full inside the check panel. 2026-10-13 R4 (build local dev, 2026-10-13): cannot-retest - The 502 from /shipments/validate could not be provoked again - about fifteen validations across FedEx, UPS and USPS on the Canada, Mexico and UK lanes all returned 200. A related case did appear and is worth the team's attention: when the FedEx sandbox returned 503, the check panel printed the raw status to the user - 'No price from the carrier: No price: FEDEX rate call failed - HTTP 503 The service is currently unavailable...'. The carrier's own sentence is fine; the 'HTTP 503' prefix is the same raw-status habit the original bug was about. 2026-10-13 R5 (build local dev, 2026-10-13 (rebuilt after R4; frontend modules dated 13:12 IST)): cannot-retest - The one-off 502 from /shipments/validate did not recur: about ten validations across USPS and FedEx in this run returned 200. The raw-status habit behind it is still visible in another place, though: whenever the FedEx sandbox rate call fails, the check panel prints 'No price from the carrier: No price: FEDEX rate call failed - HTTP 503 The service is currently unavailable...' (and once 'HTTP 500 GENERIC.ERROR'), twice in the same panel. That is now logged as its own bug so it can be fixed independently of the toast. 2026-10-14 R6 (build local dev, 2026-10-14 (order-form modules reloaded 13:17 IST)): fixed - R6: the real 502 never recurred, so the failure was simulated in the page: the next POST /api/v1/shipments/validate was answered with an HTML 502 Bad Gateway. The toast now reads 'Something went wrong - Backend is temporarily unavailable - please try again in a moment.' with no HTTP wording, and the form stays as it was. (The previous check panel stays open with its old results while the toast shows.) | Z17: Fixed | AB17: Fixed on dev (cleanServerMessage): cleanServerMessage already strips HTTP prefix. One-off 502 not reproducible. | AC17: 2026-10-13
A18: BUG-017 | C18: Query | D18: API | E18: Orders | F18: Order detail (GET /api/v1/orders/{id}) | G18: shippingDetails.weight | H18: Order API: shippingDetails.weight holds one box's weight on two-box orders, not the shipment total - intended? | I18: 1. GET /api/v1/orders/934190 (2 boxes of 2 lb) 2. Read data.shippingDetails.weight and data.orderDetails.packageCount | J18: All 97 two-box orders of the run, e.g. #934190 (2 x 2 lb), #934172 (THB 2 x 5 lb) | K18: If the field is the order weight, it should be the total (4 lb, 10 lb); if it is per box, the name or docs should say so and per-box weights should be available. | L18: weight 2 for #934190 and 5 for #934172; on all 97 two-box orders it equals one box's weight. | N18: /api/v1/orders/{id} | O18: Always (97 of 97) | P18: Not captured | R18: admin (ADMIN) | T18: 2026-10-11 | U18: R1 | V18: S004 | X18: Reopened | Y18: 2026-10-12 R3: still-failing - Unchanged. GET /api/v1/orders/934190 returns orderDetails.packageCount 2 with shippingDetails.weight 2 (the shipment is 2 boxes of 2 lb, so the total is 4); #934172 returns packageCount 2 with weight 5 against a 10 lb total. shippingDetails still carries only city, state, zipCode, shipVia, weight, shipViaDescription and intlYn - there is no per-box weight array and no renamed field, so the ambiguity the bug asked about is unresolved. 2026-10-13 R4 (build local dev, 2026-10-13): still-failing - Unchanged. shippingDetails.weight still holds one box's weight on multi-box orders: #934190 packageCount 2 / weight 2 (total 4), #934172 packageCount 2 / weight 5 (total 10), and the new #934191 packageCount 2 / weight 3 (total 6). No per-box weight array and no renamed field have been added. 2026-10-13 R5 (build local dev, 2026-10-13 (rebuilt after R4; frontend modules dated 13:12 IST)): still-failing - Fixed for every GENERATED order checked, not for orders that never got a label. New two-box order #934192 (2 x 5 lb) reports shippingDetails.weight 10, and the backfill corrected the old ones: #934190 now 4 (was 2) and #934172 now 10 (was 5). But the two-box ERROR orders still hold one box's weight: #934191 reports 3 for a 6 lb shipment (2 x 3 lb) and #934106 reports 5 for 10 lb (2 x 5 lb), both unchanged since R4. The backfill appears to work from label batches, which ERROR orders do not have, so the field still means 'total' or 'one box' depending on the order's status. The new FedEx two-box order #934193 (2 x 3 lb FedEx Tube) also reports weight 6, so new orders are correct on both carriers tried. 2026-10-14 R6 (build local dev, 2026-10-14 (order-form modules reloaded 13:17 IST)): still-failing - R6: unchanged for orders that never got a label: ERROR orders #934191 (2 boxes, 2 x 3 lb) reports shippingDetails.weight 3 and #934106 (2 x 5 lb) reports 5. GENERATED orders stay correct: #934190 4, #934172 10, #934192 10. 2026-10-16 R7 (build local dev, 2026-10-16): still-failing - unchanged for orders that never got a label: ERROR orders #934191 (packageCount 2, 2 x 3 lb) and #934106 (packageCount 2, 2 x 5 lb) still report shippingDetails.weight 3 and 5. GENERATED orders stay correct: #934190 4, #934172 10, #934192 10. Matches the developers' own note that the ERROR path was missed by the backfill. | Z18: Deferred | AB18: Deferred to next round: Code fix covers new orders; ERROR path missed by V150 — needs broader backfill. | AC18: 2026-10-13
A19: BUG-018 | C19: Query | D19: Orders | E19: New order | F19: New order form (international) | G19: Shipment check panel | H19: Shipment check (USPS to UK and Mexico): every check says 'USPS normalised the address; review before shipping' without showing what changed | I19: 1. Open Orders and click + New shipment (/orders/new) 2. Client: MKL246 (ship from 3PL-EAST, the client default) 3. Carrier: USPS 4. Ship to the UK (1 Canada Square, London E14 5AB) or Mexico (as above) 5. Complete the form and click Validate shipment | J19: UK #934147-#934151, Mexico #934186-#934190 (10 of 10); not shown for Canada | K19: Show the normalised address (or the difference) so it can be reviewed, and only flag it when something changed. | L19: 'Ready to ship — 1 thing to review: USPS normalised the address; review before shipping.' with no address shown. | N19: /orders/new | O19: Always (10 of 10 UK/Mexico USPS checks) | P19: BUG-018.png, BUG-018-R7.jpg | R19: admin (ADMIN) | T19: 2026-10-11 | U19: R1 | V19: S001 | X19: Reopened | Y19: 2026-10-12 R3: still-failing - Unchanged. USPS Priority Mail Intl to the UK still ends with 'Ready to ship - 1 thing to review' and, under Carrier check, the single line 'USPS normalised the address; review before shipping.' Expanding the row shows nothing more - the normalised address and the difference are still not shown, and the note appears whether or not anything changed. 2026-10-13 R4 (build local dev, 2026-10-13): still-failing - Unchanged on the UK lane. USPS Priority Mail Intl to London E14 5AB ends with 'Ready to ship - 1 thing to review' and, under Carrier check, the single line 'USPS normalised the address; review before shipping.' No normalised address and no difference are shown. Worth noting the same shipment to Canada produced no normalisation note at all and passed cleanly, so the note is lane-specific rather than unconditional. 2026-10-13 R5 (build local dev, 2026-10-13 (rebuilt after R4; frontend modules dated 13:12 IST)): still-failing - Unchanged on the UK lane. USPS Priority Mail Intl to 1 Canada Square, London E14 5AB still ends with 'Ready to ship - 1 thing to review' and, under Carrier check, only the line 'USPS normalised the address; review before shipping.' No normalised address and no difference are shown. The validate response explains why the screen cannot show more: carrier.matchLevel is 'CORRECTED' with message 'Full Address Verified.' and warnings ['USPS normalised the address; review before shipping.'], while the top-level address field is null - the corrected address is not returned to the page at all. The Mexico lane behaves the same: USPS Priority Mail Intl to Av Paseo de la Reforma 222, Ciudad de Mexico CMX 06600 gives the identical single line under Carrier check, again with address null and matchLevel 'CORRECTED' in the response. 2026-10-14 R6 (build local dev, 2026-10-14 (order-form modules reloaded 13:17 IST)): still-failing - R6: unchanged on the UK lane. USPS Priority Mail Intl, MKL246 to QA-1014-R6 Recipient, 1 Canada Square, London E14 5AB GB, THB-PACKAGE 2 lb: 'Ready to ship - 1 thing to review', Carrier check 'USPS normalised the address; review before shipping.' The validate response has overall WARN 'USPS suggests a corrected address.', carrier.matchLevel CORRECTED, message 'Full Address Verified.' and address null, so the page still has no corrected address to show. 2026-10-16 R7 (build local dev, 2026-10-16): still-failing - USPS Priority Mail Intl, MKL246 to QA-1016 Recipient, 1 Canada Square, London E14 5AB GB, THB-PACKAGE 2 lb, DAP: 'Ready to ship - 1 thing to review', Carrier check 'USPS normalised the address; review before shipping.' with no address and no difference shown. A second UK address (10 Downing Street, London SW1A 2AA) gives the identical line, so the note is not tied to a real change either. Validate response: overall WARN 'USPS suggests a corrected address.', carrier.matchLevel CORRECTED, message 'Full Address Verified.', top-level address null. | Z19: Fixed | AB19: Fixed on dev (70ae2636 + 1e36810b): SERA path shipped 2026-10-12; SWSIM intl path hardened 2026-10-13 (seraAddressesEqual check so UK lane only fires when SWSIM actually normalised). | AC19: 2026-10-15
A20: BUG-019 | C20: Query | D20: Orders | E20: New order | F20: New order form (international) | G20: Shipment check panel | H20: Shipment check (FedEx to UK): billed-weight notes of 68, 52 and 22 lb seen during the run, about 3-9 times the figures for the same boxes to Mexico | I20: 1. Open Orders and click + New shipment (/orders/new) 2. Client: MKL246 (ship from 3PL-EAST, the client default) 3. Carrier: FedEx 4. Ship to: 1 Canada Square, London E14 5AB, United Kingdom 5. Service level: FedEx International Priority 6. Packaging FedEx Tube, Weight 3; Add another box; Apply box 1 to all 7. Complete customs, importer and items; click Validate shipment | J20: Run: #934115 and #934122 (2 tubes 38x6x6 in): 68 lb; #934121 (2 Paks): 52 lb; #934117 and #934124 (2 boxes 12x9x4 in): 22 lb. Mexico for the same boxes: 19.68, 5.52 and 6.22 lb | K20: The same boxes give the same billed weight on every lane (19.68 lb for the two tubes). | L20: During the run the UK checks showed billed weights of 68 lb (two tubes), 52 lb (two Paks) and 22 lb (two 12x9x4 in boxes: '22 lb - charged on box size, not the 4 lb it weighs'). On retest 2026-10-12 the same UK tube shipment showed the expected 19.68 lb, so it did not reproduce. Raised so the team can check whether the figure comes from the FedEx sandbox response or the app. | N20: /orders/new | O20: 5 times during the run; 0 of 1 on retest | P20: BUG-019.jpg, BUG-019-2.jpg, BUG-019-3.png | R20: admin (ADMIN) | T20: 2026-10-11 | U20: R1 | V20: S001 | X20: Closed | Y20: 2026-10-12 R3: fixed - Did not reproduce, and the figure is now explained. FedEx International Priority to London E14 5AB with two FedEx Tubes of 3 lb shows 'Billed weight 19.68 lb - charged on box size, not the 6 lb it weighs' - the expected dimensional figure, with the reason printed beside it. The 68 lb / 52 lb / 22 lb readings of the original run did not recur on any lane tried. 2026-10-13 R4 (build local dev, 2026-10-13): fixed - No inflated billed weight seen on any lane this run. FedEx International Priority to Mexico with a 4 lb THB-PACKAGE reported 'Billed weight 4 lb', and the 2026-10-12 check of the original repro (two FedEx Tubes to London) gave the expected 19.68 lb with the explanation 'charged on box size, not the 6 lb it weighs'. 2026-10-13 R5 (build local dev, 2026-10-13 (rebuilt after R4; frontend modules dated 13:12 IST)): fixed - Regression check passed on the original repro: FedEx International Priority to 1 Canada Square, London E14 5AB with two FedEx Tubes (38x6x6 in, 3 lb each) gives 'Billed weight 19.68 lb - charged on box size, not the 6 lb it weighs' (validate response: billableWeight 19.68, actualWeight 6, dimensional true), the same figure as Mexico. No inflated billed weight seen. | Z20: New
A21: BUG-020 | C21: Suggestion | D21: Orders | E21: New order | F21: New order form (international) | G21: Label size (FedEx) | H21: New shipment (FedEx): Label size stays 'Thermal stock 4×6' when Label type is switched to PDF | I21: 1. Open Orders and click + New shipment (/orders/new) 2. Client: MKL246 (ship from 3PL-EAST, the client default) 3. Carrier: FedEx; any international destination 4. Change Label type from ZPLII (Zebra) to PDF 5. Look at Label size | J21: All FedEx shipments of the run were set to Paper 4x6 by hand | K21: Switching to PDF moves Label size to a paper size (for example Paper 4x6). | L21: Label size remains 'Thermal stock 4×6' next to Label type 'PDF (vector, sharp)'. | N21: /orders/new | O21: Always | P21: BUG-020.jpg | R21: admin (ADMIN) | T21: 2026-10-11 | U21: R1 | V21: S001 | X21: Closed | Y21: 2026-10-12 R3: fixed - Changing Label type from ZPLII (Zebra) to PDF (vector, sharp) now moves Label size from 'Thermal stock 4x6' to 'Paper 4x6' on its own. 2026-10-13 R4 (build local dev, 2026-10-13): fixed - Switching Label type from ZPLII (Zebra) to PDF (vector, sharp) moves Label size from 'Thermal stock 4x6' to 'Paper 4x6' on its own. 2026-10-13 R5 (build local dev, 2026-10-13 (rebuilt after R4; frontend modules dated 13:12 IST)): fixed - Regression check passed with the renamed options: switching FedEx Label type from 'ZPL (thermal)' to 'PDF (plain)' moves Label size from 'Thermal stock 4x6' to 'Paper 4x6' on its own. | Z21: New
A22: BUG-021 | C22: Suggestion | D22: Orders | E22: New order | F22: Importer & broker override dialog | G22: Type (Business / Receiver) | H22: Importer & broker override: choosing Type 'Receiver · DAP' leaves every field empty instead of using the ship-to details | I22: 1. Open Orders and click + New shipment (/orders/new) 2. Client: MKL246 (ship from 3PL-EAST, the client default) 3. Carrier: FedEx 4. Ship to: Full name QA Test Recipient, Company QA Test Co, Address line 1 290 Bremner Blvd, Country Canada (CA), Phone 4165550100, State / region ON, City Toronto, Postal code M5V 3L9 5. Importer of record & customs broker > Add 6. Type: Receiver · DAP | J22: Every international shipment of the run (MKL246 has no importer profile for CA, GB or MX) | K22: Receiver fills (or offers to fill) name, address, city, state, post code and phone from Ship to. | L22: All fields stay empty apart from Country; all 7 values had to be typed for each of the 128 orders. | N22: /orders/new | O22: Always | P22: BUG-021.jpg, BUG-021-2.jpg, BUG-021-3.png | R22: admin (ADMIN) | T22: 2026-10-11 | U22: R1 | V22: S002 | X22: Closed | Y22: 2026-10-12 R3: fixed - Importer of record & customs broker > Add > Type 'Receiver - DAP' now fills Name (QA Test Recipient), Address 1 (290 Bremner Blvd), City (Toronto), State (ON), Post code (M5V 3L9), Country (CA) and Phone (4165550100) from Ship to. Only the optional Contact box stays empty. 2026-10-13 R4 (build local dev, 2026-10-13): fixed - Importer of record & customs broker > Add > Type 'Receiver - DAP' fills Name, Address 1, City, State, Post code, Country and Phone from Ship to; only the optional Contact box stays empty. 2026-10-13 R5 (build local dev, 2026-10-13 (rebuilt after R4; frontend modules dated 13:12 IST)): fixed - Regression check passed: Importer of record & customs broker > Add > Type 'Receiver - DAP' fills Name QA Test Recipient, Address 1 1 Canada Square, City London, Post code E14 5AB, Country GB and Phone 2079460000 from Ship to; State (empty on Ship to) and Contact stay empty. | Z22: New
A23: BUG-022 | B23: Low | C23: Functional | D23: Settings | E23: Organization > Clients | F23: Clients list | G23: Search code, name, city | H23: Clients search: '%' and '_' work as wildcards, so searching for them lists clients that do not contain them | I23: 1. Open Settings > Clients (/settings/clients) 2. Type % in the box 'Search code, name, city...' and wait for the list 3. Replace it with _ and wait 4. Replace it with MKL_46 and wait 5. Replace it with M%6 and wait 6. Clear the search, click Filters, type _ in Code contains and wait; clear it and type % in City contains | J23: Search terms: %, _, MKL_46, M%6. Clients on file: MKL246 (MKL, Zeeland MI), THB000 (Thoroughbred Fulfillment LLC, Zeeland MI) | K23: The search matches the text typed. No client code, name or city contains % or _, so each of these four searches should show 'No clients match the current filters.' Client codes may contain '_' (the Add Client hint says 'Letters, digits, '-', '_''), so a code search with '_' must not also match other characters in that position. | L23: '%' and '_' each list both clients ('Showing 2 of 2 clients'). 'MKL_46' and 'M%6' each list MKL246 ('Showing 1 of 1 client'). The Filters panel has the same fault: Code contains '_' and City contains '%' each list both clients. Settings > Logs, Search entity key behaves the same: '%' (sent as entityKey=%25) returns all 34,622 entries and 'QA13_5' finds the QA13R5 rows. Email Delivery Log, Recipient contains: '%' (recipient=%25) returns all 7 rows. | M23: GET /api/v1/clients?page=0&size=25&sortBy=code&sortDirection=ASC&search=%25 -> 200, 2 rows GET /api/v1/clients?...&search=_ -> 200, 2 rows GET /api/v1/clients?...&search=MKL_46 -> 200, 1 row (MKL246) The term reaches the server intact, so the server most likely uses it in a SQL LIKE pattern without escaping % and _. | N23: http://localhost:5173/settings/clients | O23: Always | P23: BUG-022.jpg | R23: admin (ADMIN) | T23: 2026-10-12 | U23: R2 | V23: S006 | W23: Settings > Organization > Warehouses > Warehouses list; Settings > Organization > Users > Users list; Settings > Activity & Logs > Logs; Settings > Activity & Logs > Email Delivery Log | X23: Closed | Y23: 2026-10-12 R3: fixed - Searching '_', '%' and 'MKL_46' now all give 'Showing 0 of 0 clients'. A normal term still works ('mkl' finds MKL246). The Filters panel is fixed too: Code contains '_' and City contains '%' both give 0 of 0. 2026-10-13 R4 (build local dev, 2026-10-13): fixed - Re-walked at 1460x847. Searching '%' returns 'No clients match the current filters' with 'Showing 0 of 0 clients'; the wildcard is no longer passed through to the query. 2026-10-13 R5 (build local dev, 2026-10-13 (rebuilt after R4; frontend modules dated 13:12 IST)): still-failing - Fixed on Clients, still failing on Warehouses, which this bug lists as also affected. Clients: '%' and 'MKL_46' in the search box both give 'No clients match the current filters' (Showing 0 of 0), and in Filters, Code contains '_' and City contains '%' each give 0 rows, while 'zEELand' still finds both clients; a SQL-style probe (' OR 1=1 --) and an HTML payload return 0 rows with no error. Warehouses (/settings/warehouses, two warehouses 3PL-EAST and QA-1013-R5-WH01): '_' and '%' each still list both warehouses although neither contains either character, so the wildcard is still passed through to the query there. 'SPRINGFIELD' and '"quoted"' match correctly. Users (/settings/users) has the same fault and is added to the affected screens: '%' and '_' in 'Search username, email, name...' each list both users (admin and manoj7000), although no username, email or name contains either character. 2026-10-14 R6 (build local dev, 2026-10-14 (order-form modules reloaded 13:17 IST)): still-failing - R6: still fixed on Clients, still failing everywhere else this bug lists. Warehouses: '%', '_' and '3PL_EAST' each list 3PL-EAST. Users: '%' and '_' each list both users. Logs, Search entity key: '%' (sent as entityKey=%25) returns all 34,627 entries, and 'QA-1014_R6' finds QA-1014-R6-WH01. Email Delivery Log, Recipient contains: '%' (recipient=%25) and '_' each show 10 of 10 rows, although no recipient contains either character, while 'verify' correctly shows 3. 2026-10-16 R7 (build local dev, 2026-10-16): fixed - R7: fixed on every screen this bug lists. Clients unchanged (fixed since R4). Warehouses: '%', '_' and '3PL_EAST' each give 'No warehouses match the current filters' (Showing 0 of 0), while '3PL-EAST' finds Central Warehouse. Users: '%' and '_' give 'No users.', 'adm' finds admin. Logs, Search entity key: '%' (entityKey=%25) and 'QA-1014_R6' give 0 entries, 'QA-1014-R6' gives 4. Email Delivery Log, Recipient contains: '%' and '_' give 'No delivery rows match those filters' (0 of 0), 'verify' gives 3 of 3. | Z23: Fixed | AB23: Fixed on dev (a601e4aa): Delivery log recipient filter now escapes % _ and query uses ESCAPE "\\". R6+1 (afeb4111+e17bf946, 2026-10-15): Spread ESCAPE '\' + escapeLike() to WarehouseRepository, AdminUserService (Criteria API) and AuditLogRepositoryCustomImpl. Delivery-log fix (a601e4aa) now matches every other search path. Test fix (46d6db84, 2026-10-15): — no code change, just test lock-in. | AC23: 2026-10-15
A24: BUG-023 | C24: Suggestion | D24: Settings | E24: Organization > Clients | F24: Clients list | G24: Columns (show/hide + pin) | H24: Clients > Columns: every column can be hidden, leaving blank rows with only the row menu (Edit, Delete) | I24: 1. Open Settings > Clients (/settings/clients) 2. Click Columns 3. Untick Code, Name, Contact, Country, Carrier accounts, Orders and Status 4. Press Esc to close the menu | J24: Default column layout; 2 clients (MKL246, THB000) | K24: At least one identifying column (for example Code) stays visible, or the last ticked column cannot be unticked, so each row still shows which client it is. | L24: All seven columns can be unticked. The grid then shows an empty header and two blank rows with only the ⋮ row menu, whose Edit and Delete act on a client the user cannot see. 'Reset layout' in the Columns menu brings the columns back. | M24: Reloading the page keeps the blank grid (column layout is remembered in the browser), so it stays until Columns > Reset layout is used. | N24: http://localhost:5173/settings/clients | O24: Always | P24: BUG-023.jpg, BUG-023-2.jpg, BUG-023-3.png | R24: admin (ADMIN) | T24: 2026-10-12 | U24: R2 | V24: S006 | X24: Closed | Y24: 2026-10-12 R3: still-failing - All seven columns can still be unticked in the Columns menu, leaving an empty header and two blank rows with only the row menu. Reset layout still brings them back. 2026-10-13 R4 (build local dev, 2026-10-13): still-failing - Unchanged. Every one of the seven columns can still be unticked in the Columns menu - no minimum is enforced and the last one is not disabled. With all seven hidden the grid shows two header-less, cell-less rows carrying only the row menu, under the line 'Showing 2 of 2 clients'. Reset layout is the only way back. 2026-10-13 R5 (build local dev, 2026-10-13 (rebuilt after R4; frontend modules dated 13:12 IST)): fixed - With Name, Contact, Country, Carrier accounts, Orders and Status unticked, the last ticked column (Code) is disabled with the title 'At least one column must stay visible', so every row still shows its client code. Reset layout restores all seven columns - but it also unpins the row-actions column until reload (logged separately as BUG-074). | Z24: Fixed | AB24: Fixed on dev (2e93fc82): Hideable-only count on the last-visible guard. Yesterday fix counted the row-actions column (hideable=false) in visibleCount so last user column could still be hidden. | AC24: 2026-10-13
A25: BUG-024 | B25: Low | C25: Usability | D25: Settings | E25: Organization > Clients | F25: Clients list | G25: Row menu > Importer / Broker | H25: Importer / Broker dialog (Clients row menu): a click on the dimmed background closes it and throws away what was typed; Esc does nothing | I25: 1. Open Settings > Clients (/settings/clients) 2. Scroll the table to the right and open the ⋮ menu on MKL246 3. Click Importer / Broker 4. Type QA-1012-IMP-BACKDROP in Importer name and QA Contact in Contact 5. Press Esc 6. Click on the dimmed background to the right of the dialog 7. Open ⋮ > Importer / Broker on MKL246 again | J25: Client MKL246; Importer name QA-1012-IMP-BACKDROP; Contact QA Contact (nothing saved) | K25: Esc and a background click behave the same way, and neither silently discards typed data: either they ask 'Discard changes?' when something has been typed, or only Cancel / X close the dialog. The Filters panel and Columns menu on the same page close on Esc. | L25: Esc does nothing (the dialog stays open, focus moves to the X button). A single click on the dimmed background closes the dialog at once with no warning; reopening shows an empty form, so everything typed is lost. | M25: No request is sent on close (nothing saved). The form is long (client and destinations, importer of record, tax identity and further sections), so one stray click loses a lot of typing. | N25: http://localhost:5173/settings/clients | O25: Always | P25: BUG-024.jpg | R25: admin (ADMIN) | T25: 2026-10-12 | U25: R2 | V25: S006 | X25: Closed | Y25: 2026-10-12 R3: still-failing - Unchanged. Esc with the cursor in Importer name does nothing; a single click on the dimmed background closes the dialog at once and the typed name is gone when it is reopened. 2026-10-13 R4 (build local dev, 2026-10-13): still-failing - Unchanged, and now inconsistent with the rest of the app. With 'QA-1013 Importer Draft' typed into Importer name, a click on the dimmed background closed the Importer / Broker dialog at once and discarded it, with no prompt. The client editor on the same screen does guard this: leaving it with unsaved changes raises 'Leave client editor? This client has unsaved changes. Leave and lose what you've edited?' with Stay / Leave. 2026-10-13 R5 (build local dev, 2026-10-13 (rebuilt after R4; frontend modules dated 13:12 IST)): fixed - Esc and a click on the dimmed background now both ask 'Discard this draft and close?' once something has been typed (QA-1013-R5 Importer Draft in Importer name). Answering Cancel keeps the dialog open with the text intact (checked for both Esc and the background); answering OK closes it. Cancel and X in the dialog still close without asking, which the bug allowed. The question is asked with the browser's own confirm box rather than the in-app Stay / Leave dialog the client editor and the order form use - logged separately as a consistency point. | Z25: Fixed | AB25: Fixed on dev (6e754e09): CustomsProfileModal ModalShell already in dev. QA R4 ran against stale bundle. | AC25: 2026-10-13
A26: BUG-025 | B26: Low | C26: UI | D26: Settings | E26: Organization > Clients | F26: Clients list | G26: Table width / row actions reachable at 1446 px | H26: Clients list: the row menu (⋮ Importer / Broker, Edit, Delete) is off-screen at a 1446 px wide window; it is only reachable by scrolling the table sideways | I26: 1. Use a browser window 1446 x 840 with the Settings menu expanded 2. Open Settings > Clients (/settings/clients) 3. Look for the ⋮ menu at the end of each row 4. Scroll the table to the right with the horizontal scrollbar under the rows | J26: Default column layout and Compact density; 2 clients | K26: The row actions are visible without sideways scrolling: the seven default columns fit, and the Status column has a wide empty area after the Active badge. | L26: The rows end at the Status column; the ⋮ menu (the only way to Edit or Delete a client) is hidden past the right edge. A horizontal scrollbar appears under the table, and the ⋮ buttons show only after scrolling right, when Code and Name scroll out of view. | M26: Window 1446 x 840, Settings menu expanded. With every column hidden (Columns menu) the ⋮ buttons appear at the right edge without scrolling, so the overflow comes from the column widths. | N26: http://localhost:5173/settings/clients | O26: Always | P26: BUG-025.jpg, BUG-025-2.jpg, BUG-025-3.jpg, BUG-025-4.jpg, BUG-025-5.png | R26: admin (ADMIN) | T26: 2026-10-12 | U26: R2 | V26: S006 | X26: Closed | Y26: 2026-10-12 R3: still-failing - Still reproduces, though not at the original width: the Claude side panel fixes this session's viewport at 1005x847, so 1446 px could not be set. At 1005 px with the default column layout the row ends at Orders and the actions column is past the right edge; the horizontal scrollbar has to be used before any row action can be reached. 2026-10-13 R4 (build local dev, 2026-10-13): still-failing - Unchanged, and my 2026-10-12 reading of 'fixed' was wrong - that check was made while the grid happened to be scrolled right. Measured from the DOM at a 1460 px window with the default layout: both Row actions buttons sit at x 1587-1615, entirely outside the viewport. The grid's own scroller is 1058 px wide against 1280 px of content, so the row menu can only be reached by scrolling the grid sideways; there is no sticky actions column. 2026-10-13 R5 (build local dev, 2026-10-13 (rebuilt after R4; frontend modules dated 13:12 IST)): fixed - At 1442 px with the Settings menu expanded and the default layout, both row-action (⋮) buttons sit at x 1347 in a sticky cell at the right edge of the grid and are clickable without scrolling (hit-tested in the DOM); the grid itself still scrolls 240 px sideways for the Status column, which is reachable by scrolling. Note that Columns > Reset layout unpins the column again until the page is reloaded (BUG-074). | Z26: Fixed | AB26: Fixed on dev (9f8a1ebe): pinnedByDefault now honoured when persisted pinning is empty — operators with pre-fix empty pinning state now get the row-actions sticky pin on first load. | AC26: 2026-10-13
A27: BUG-026 | B27: Low | C27: UI | D27: Settings | E27: Organization > Clients | F27: Clients list | G27: Sort by Code | H27: Clients list sorting: after the third click on a header the arrow disappears, but the list is still sorted by Code ascending, so the next click on Code appears to do nothing | I27: 1. Open Settings > Clients (/settings/clients); the Code header shows an up arrow (Code ascending) 2. Click the Code header (Code descending: THB000 first) 3. Click the Code header again: no arrow is shown and the rows are MKL246, THB000 4. Click the Code header once more | J27: 2 clients (MKL246, THB000) | K27: Each click visibly changes the sort, and the header arrow always matches the order shown: either the third click returns to 'Code ascending' with its arrow (as on page load), or the 'unsorted' state shows rows in a different, unsorted order. | L27: After the second click the header shows no arrow although the rows are in Code ascending order (the page-load state, which shows an arrow). The following click only brings the arrow back; the rows do not move. Cycling Orders (descending, ascending, then a third click) ends in the same arrow-less Code ascending state. | M27: The 'no arrow' state requests GET /api/v1/clients?page=0&size=25&sortBy=code&sortDirection=ASC, the same request as page load and as 'Code ascending'. | N27: http://localhost:5173/settings/clients | O27: Always | P27: BUG-026.png | R27: admin (ADMIN) | T27: 2026-10-12 | U27: R2 | V27: S006 | X27: Closed | Y27: 2026-10-12 R3: fixed - The Code header now cycles between two states only. Three clicks from the default gave descending (THB000 first, arrow down), ascending (MKL246 first, arrow up), descending again - the arrow matches the order every time and the arrow-less state is gone. 2026-10-13 R4 (build local dev, 2026-10-13): fixed - Clicking the Code header three times now leaves a visible sort arrow and a list that matches it: THB000 above MKL246, with the request GET /api/v1/clients?...sortBy=code&sortDirection=DESC. The header cycles between ASC and DESC with the arrow always shown; the silent third state is gone. 2026-10-13 R5 (build local dev, 2026-10-13 (rebuilt after R4; frontend modules dated 13:12 IST)): fixed - Regression check passed: three clicks on Code go descending (THB000 first), ascending, descending, with aria-sort and the arrow always matching the rows; Name sorts alphabetically and Orders numerically (33467 before 407); Contact, Country, Carrier accounts and Status are not sortable. | Z27: New
A28: BUG-027 | B28: Low | C28: Usability | D28: Settings | E28: Organization > Clients | F28: Client wizard (Add / Edit) | G28: Defaults > Timezone (IANA search and locate button) | H28: Client wizard > Timezone: searching 'Kolkata' or 'Kyiv' finds nothing; the list only has the old names Asia/Calcutta and Europe/Kiev | I28: 1. Open Settings > Clients and click + Add Client 2. In Defaults > Timezone type Kolk 3. Replace it with Calcutta 4. Replace it with Kyiv, then with Kiev 5. Click the locate button 'Detect timezone from browser' (browser set to India time) | J28: Timezone search terms Kolk, Calcutta, Kyiv, Kiev | K28: The field asks for an IANA name ('IANA (e.g. America/New_York)'); the current IANA names Asia/Kolkata and Europe/Kyiv are offered (old aliases may also match), so a user searching the city's current name finds it. | L28: 'Kolk' and 'Kyiv' show 'No timezone matches ...'. 'Calcutta' offers Asia/Calcutta (UTC+05:30) and 'Kiev' offers Europe/Kiev. The locate button also fills Asia/Calcutta. | M28: The list appears to come from the browser's own time-zone list, which in Chrome still uses the old aliases. | N28: http://localhost:5173/settings/clients/new | O28: Always | P28: BUG-027.png, BUG-027-2.jpg, BUG-027-3.png, BUG-027-4.jpg, BUG-027-5.png | R28: admin (ADMIN) | T28: 2026-10-12 | U28: R2 | V28: S040 | X28: Closed | Y28: 2026-10-12 R3: still-failing - Half fixed. 'Kyiv' now finds Europe/Kiev, so an alias has been added there, but 'Kolk' still shows 'No timezone matches "Kolk".' - Asia/Kolkata is still missing. 2026-10-13 R4 (build local dev, 2026-10-13): fixed - The timezone list carries the modern names and keeps the old ones as aliases. Searching 'Kolkata' returns both Asia/Calcutta and Asia/Kolkata (UTC+05:30); searching 'Kyiv' returns Europe/Kiev and Europe/Kyiv (UTC+03:00). 2026-10-13 R5 (build local dev, 2026-10-13 (rebuilt after R4; frontend modules dated 13:12 IST)): fixed - Regression check passed: on the new-client wizard, Timezone search 'Kolkata' lists Asia/Calcutta and Asia/Kolkata (UTC+05:30), 'Kyiv' lists Europe/Kiev and Europe/Kyiv (UTC+03:00), and 'toronto' (lower case) finds America/Toronto. | Z28: New
A29: BUG-028 | B29: Medium | C29: Validation | D29: Settings | E29: Organization > Clients | F29: Client wizard (Add / Edit) | G29: Return address: Same as Ship From / own address | H29: Client wizard > Return address: a ZIP+4 cannot be typed - the field stops at 9 characters while its own hint shows the 10-character form 12345-6789 | I29: 1. Open Settings > Clients and click + Add Client 2. Fill step 1 Identity and pick a warehouse on step 2 Ship From, then go to step 3 Return address 3. Untick 'Same as Ship From' 4. Type 60601-1234 in ZIP | J29: ZIP typed: 60601-1234 (10 characters). Hint under the field: 'Format: 12345 or 12345-6789 - max 9 chars - UPS' | K29: A ZIP+4 in the form the hint shows (12345-6789) can be typed and is accepted; if the carrier limit is 9 digits, the hyphen should not count towards it. | L29: The input has maxlength 9, so typing stops after '60601-123'. The field then shows the error 'Postal code doesn't match the US format.' and Next stays disabled, so a US ZIP+4 return address cannot be saved at all. | M29: input maxlength 9, value after typing 60601-1234: '60601-123'. The same 9-character limit is on the ZIP field of the Ship From / Return address block. Phone behaves the same way: maxlength 15 truncates '+1 (312) 555-0100' to '+1 (312) 555-01', but no error is shown for that. | N29: http://localhost:5173/settings/clients/new | O29: Always | P29: BUG-028.jpg, BUG-028-2.jpg, BUG-028-3.png | R29: admin (ADMIN) | T29: 2026-10-12 | U29: R2 | V29: S040 | X29: Closed | Y29: 2026-10-12 R3: fixed - The ZIP field now has maxlength 10 and its hint reads 'Format: 12345 or 12345-6789 - max 10 chars - USPS / UPS'. Typing 60601-1234 leaves the full value with no error. 2026-10-13 R4 (build local dev, 2026-10-13): fixed - Return address ZIP now accepts the full ZIP+4: 60601-1234 (10 characters) is held in the field, and the hint reads 'Format: 12345 or 12345-6789 - max 10 chars - USPS / UPS'. Field and hint agree. 2026-10-13 R5 (build local dev, 2026-10-13 (rebuilt after R4; frontend modules dated 13:12 IST)): fixed - Regression check passed: on step 3 Return address with 'Same as Ship From' unticked, ZIP has maxlength 10 and holds 60601-1234 in full; the hint reads 'Format: 12345 or 12345-6789 - max 10 chars - USPS / UPS' and Next is enabled. | Z29: New
A30: BUG-029 | B30: Low | C30: Content | D30: Settings | E30: Organization > Clients | F30: Client wizard (Add / Edit) | G30: Carrier accounts grid for the client (+ Add Account, default star) | H30: Client wizard > Carriers: the UPS account number hint and its error message give different rules ('exactly 6 alphanumerics' vs '6-10 letters or digits') | I30: 1. Open Settings > Clients and click + Add Client 2. Fill step 1, pick a warehouse on step 2, go on to step 4 Carriers 3. Click + Add carrier account; Carrier is UPS 4. Read the grey hint under Account number 5. Type 12 in Account number and click into Client ID 6. Replace it with QA10127890123 and click into Client ID | J30: Carrier UPS; Account number 12, then QA1012!! (saved as QA1012) | K30: The hint and the error state the same rule, so the user knows whether a 7-10 character UPS number is allowed. | L30: The grey hint reads 'UPS shipper numbers are exactly 6 alphanumerics.' while the red error, shown for a shorter value, reads 'UPS shipper number is 6-10 letters or digits'. The field itself stops at 6 characters (typing QA10127890123 leaves QA1012), so the error message is the wrong one and tells the user to try lengths the field will not accept. DHL Express has the same mismatch: hint 'DHL Express account numbers are up to 9 digits.' against error 'DHL Express account number is 9-12 digits', and the field accepts letters (QA1012QA1) although both texts say digits. | M30: Account number input caps at 6 characters for UPS and strips punctuation as typed (QA1012!! becomes QA1012). Only the error text disagrees with the hint and with the field's own behaviour. | N30: http://localhost:5173/settings/clients/new | O30: Always | P30: BUG-029.jpg, BUG-029-2.png, BUG-029-3.jpg, BUG-029-4.png, BUG-029-5.png, BUG-029-R7-letters.png, BUG-029-R7.png | R30: admin (ADMIN) | T30: 2026-10-12 | U30: R2 | V30: S040 | X30: Reopened | Y30: 2026-10-12 R3: still-failing - Fixed for UPS: the hint now reads 'UPS shipper numbers are 6-10 letters or digits.', matching the error, and a 10-character number is accepted. DHL Express still disagrees with itself - the grey hint says 'DHL Express account numbers are up to 9 digits.' while the error says 'DHL Express account number is 9-12 digits'. 2026-10-13 R4 (build local dev, 2026-10-13): still-failing - The hint-versus-error mismatch is fixed for both carriers: UPS now reads '6-10 letters or digits (UPS shipper #)' with the field capped at maxlength 10 (typing QA10137890123 leaves QA10137890), and DHL Express reads '9-12 digits (DHL account #)' against the error 'DHL Express account number is 9-12 digits'. What remains is the other half of the original finding: the DHL field still accepts letters - QA1013QA1013 was held and rejected only on length, not on being non-numeric, although both the placeholder and the error say digits. 2026-10-13 R5 (build local dev, 2026-10-13 (rebuilt after R4; frontend modules dated 13:12 IST)): still-failing - Fixed for UPS and DHL, but the same fault now shows on FedEx, which the fix comment says it covers. UPS: placeholder '6-10 letters or digits (UPS shipper #)', hint 'UPS shipper numbers are 6-10 letters or digits.', error for '12' 'UPS shipper number is 6-10 letters or digits', field capped at 10 (QA10137890123 -> QA10137890) - all agree. DHL Express: inputMode numeric, pattern [0-9]{9,12}, letters stripped as typed (QA1013QA1013 -> 10131013), hint and error both '9-12 digits'. FedEx (new client QA-1013-R5-CL01, carrier form on step 4): the placeholder reads 'Up to 12 digits (FedEx account #)', the error on blur reads 'FedEx account number is exactly 9 digits', and the field itself holds up to 12 letters or digits (pattern [0-9A-Za-z]{1,12}, no numeric inputMode) - QA740561111 is kept as typed. Three different rules for one field, which is what this bug is about. Minor: a value typed for one carrier is carried over when the carrier is changed (QA13R5 typed for UPS stays in the DHL field); it is then caught on blur with the DHL error, so nothing invalid can be staged. 2026-10-14 R6 (build local dev, 2026-10-14 (order-form modules reloaded 13:17 IST)): cannot-retest - R6: not re-walked. The client editor (/settings/clients/new and /settings/clients/{code}) failed to compile from about 14:00 IST to the end of the run (15:38): '[plugin:vite:oxc] Transform failed ... src/components/ClientEditorPage.tsx:1515:13 Expected , or ) but found Identifier' - a developer edit in progress at the Markup step. 2026-10-16 R7 (build local dev, 2026-10-16): still-failing - R7: fixed for UPS and DHL, still failing for FedEx. Client wizard (+ Add Client > step 4 Carriers > + Add carrier account). UPS: placeholder '6-10 letters or digits (UPS shipper #)', hint 'UPS shipper numbers are 6-10 letters or digits.', error for '12' 'UPS shipper number is 6-10 letters or digits', field capped at 10 (QA10167890123 -> QA10167890) - all agree. DHL Express: placeholder '9-12 digits (DHL account #)', inputMode numeric, letters are stripped as typed (QA1016QA1016 -> 10161016), error '9-12 digits'. FedEx: the dev change ('field physically cannot hold letters') is not there - the placeholder reads 'Up to 12 digits (FedEx account #)', the field has no numeric inputMode and holds 12 letters or digits (QA740561111234 -> QA7405611112; 740561111234 is kept as typed), and the error on leaving the field reads 'FedEx account number is exactly 9 digits'. Three different rules for the one FedEx field. A value typed for one carrier is also carried over when the carrier is changed (QA10167890 from UPS stayed in the DHL field and was flagged on blur). | Z30: Fixed | AB30: Fixed on dev (3a9a749e): DHL/FEDEX account input strips non-digits onChange + inputMode=numeric so the field physically cannot hold letters. Test fix (46d6db84, 2026-10-15): tests now assert UPS maxLength 10 + DHL maxLength 12 to match the 6-10 / 9-12 widening. | AC30: 2026-10-15
A31: BUG-030 | B31: Medium | C31: Functional | D31: Settings | E31: Organization > Clients | F31: Client wizard (Add / Edit) | G31: Carrier accounts grid for the client (+ Add Account, default star) | H31: Client wizard > Carriers: Cancel on the carrier account form keeps everything typed, including the client secret, and + Add carrier account reopens the discarded draft | I31: 1. Open Settings > Clients and click + Add Client 2. Fill step 1 Identity and pick a warehouse on step 2 Ship From, then go to step 4 Carriers 3. Click + Add carrier account 4. Choose carrier DHL Express, type an account number, a client id and a client secret 5. Click Cancel - the list shows 'No carrier accounts staged yet' 6. Click + Add carrier account again | J31: Carrier DHL Express, account number QA1012QA1, test client id and client secret created for this run (local SANDBOX placeholders) | K31: Cancel discards the draft, so the next + Add carrier account opens an empty form on the default carrier - as the empty-state text implies. | L31: The list is emptied but the form is not: reopening it shows the cancelled carrier, account number, client id and the filled client secret. Typing an account number then appends to the retained one (QA1012 typed into a field already holding QA1012 gives QA1012QA1), so a stale credential can be staged against the wrong carrier without the user noticing. | M31: Nothing is sent on Cancel; the draft is only held in the page. The retained secret stays masked but is still submitted if the user clicks Add to list. | N31: http://localhost:5173/settings/clients/new | O31: Always | P31: BUG-030.jpg | R31: admin (ADMIN) | T31: 2026-10-12 | U31: R2 | V31: S040 | X31: Closed | Y31: 2026-10-12 R3: fixed - Cancel now clears the draft completely: reopening + Add carrier account gives an empty form on the default carrier, with the account number, client id and secret all blank. 2026-10-13 R4 (build local dev, 2026-10-13): fixed - Filled the carrier form (DHL Express, account 123456789, client id and secret), clicked Cancel, then + Add carrier account again: the form reopens empty on the default carrier UPS, with account number, client id and client secret all blank. No stale credential is retained. 2026-10-13 R5 (build local dev, 2026-10-13 (rebuilt after R4; frontend modules dated 13:12 IST)): fixed - Regression check passed: with FedEx, an account number, a client id and a client secret typed, Cancel and then + Add carrier account reopens an empty form on the default carrier UPS - account number, client id and secret (length 0) all blank. | Z31: New
A32: BUG-031 | B32: Low | C32: Usability | D32: Settings | E32: Organization > Clients | F32: Client wizard (Add / Edit) | G32: Carrier accounts grid for the client (+ Add Account, default star) | H32: Client wizard > Carriers: 'Add to list' greys out with the tooltip 'Fix the highlighted fields to continue' while no field is highlighted | I32: 1. Open Settings > Clients and click + Add Client; fill step 1 and step 2 2. On step 4 Carriers click + Add carrier account 3. Choose carrier DHL Express and type the account number QA1012QA1 (letters and digits) 4. Fill Client ID and Client secret 5. Look at the Add to list button and hover over it | J32: Carrier DHL Express, account number QA1012QA1; hint under the field: 'DHL Express account numbers are up to 9 digits.' | K32: Either the account number is accepted, or the field that fails is marked in red with its message, so the user can see what to fix. | L32: Add to list is greyed and its tooltip says 'Fix the highlighted fields to continue', but no field is red and no message is shown. The value only becomes acceptable after the carrier is changed to UPS or the letters are removed, which the user has to work out for themselves. | M32: The button is not really disabled (disabled=false) - it only looks greyed and carries the tooltip, so a click gives no feedback either. | N32: http://localhost:5173/settings/clients/new | O32: Always | P32: BUG-031.jpg | R32: admin (ADMIN) | T32: 2026-10-12 | U32: R2 | V32: S040 | X32: Closed | Y32: 2026-10-12 R3: fixed - With carrier DHL Express and the account number QA1012QA1, the field is now outlined in red with 'DHL Express account number is 9-12 digits' underneath, so the tooltip 'Fix the highlighted fields to continue' now matches what is on screen. 2026-10-13 R4 (build local dev, 2026-10-13): fixed - Add to list with the form incomplete now marks each failing field in red with its own message - 'Account number is required' under Account number and 'Client ID is required' under Client ID - and only then greys the button. The reason is visible instead of hidden behind a tooltip. 2026-10-13 R5 (build local dev, 2026-10-13 (rebuilt after R4; frontend modules dated 13:12 IST)): fixed - Regression check passed: Add to list on the empty form marks Account number ('Account number is required'), Client ID ('Client ID is required') and Client secret ('Client secret is required') in red; the button's title then reads 'Fix the highlighted fields to continue' with the fields actually highlighted. | Z32: New
A33: BUG-032 | B33: Low | C33: Content | D33: Settings | E33: Organization > Clients | F33: Client wizard (Add / Edit) | G33: Markup: kind (Percent / Flat), Value, Currency, Preview, Save markup | H33: Creating a client shows the raw error code MARKUP_REQUIRED_FOR_CLIENT in the 'Heads up' message | I33: 1. Create a client through Settings > Clients > + Add Client, skipping the Markup step 2. Read the 'Heads up' toast shown after Submit | J33: Client QA-1012-CL01 created with no billing markup | K33: The message explains in words that labels will be refused until a billing markup is set; the internal code belongs in the log, not in the message. | L33: 'Set a billing markup for QA-1012-CL01 on the Markup tab before generating labels - MARKUP_REQUIRED_FOR_CLIENT will otherwise reject every label call for this client.' | M33: The rest of the sentence already says what happens, so the code adds nothing for the user. The same warning is useful on the Markup step itself, which is only marked amber. | N33: http://localhost:5173/settings/clients/new | O33: Always | P33: BUG-032.jpg, BUG-032-2.jpg, BUG-032-3.png | R33: admin (ADMIN) | T33: 2026-10-12 | U33: R2 | V33: S040 | X33: Closed | Y33: 2026-10-12 R3: cannot-retest - The 'Heads up' toast could not be read this time: toasts now clear themselves after about ten seconds (BUG-037 is fixed) and it had gone before the screen could be captured. The Markup step itself carries no such wording. Worth one more look the next time a client is created. 2026-10-13 R4 (build local dev, 2026-10-13): fixed - Creating QA-1013-CL01 now shows: 'Heads up - Set a billing markup for QA-1013-CL01 on the Markup tab before generating labels - otherwise every label call for this client will be rejected until one is configured.' The raw MARKUP_REQUIRED_FOR_CLIENT code is gone from the message. 2026-10-13 R5 (build local dev, 2026-10-13 (rebuilt after R4; frontend modules dated 13:12 IST)): fixed - Regression check passed: creating QA-1013-R5-CL02 with no billing markup raises 'Heads up - Set a billing markup for QA-1013-R5-CL02 on the Markup tab before generating labels - otherwise every label call for this client will be rejected until one is configured.', next to 'Done - Client QA-1013-R5-CL02 created.', '1 carrier account saved.' and '1 mapping saved.' (with a 'Dismiss all' link). No raw error code anywhere; the list row's warning icon carries the same wording. | Z33: Fixed | AB33: Fixed on dev (errorMessages entry present): MARKUP_REQUIRED_FOR_CLIENT friendly entry exists; could not retest. | AC33: 2026-10-13
A34: BUG-033 | B34: Low | C34: Content | D34: Settings | E34: Organization > Clients | F34: Client wizard (Add / Edit) | G34: Return address: Same as Ship From / own address | H34: Client wizard > Return address: the State limit is credited to USPS in both modes but changes from 'max 2 chars' to 'max 5 chars' on a client with no USPS account | I34: 1. Open Settings > Clients and click + Add Client 2. On step 3 Return address untick 'Same as Ship From' and read the hint under STATE: 'max 2 chars - USPS' 3. Finish the wizard with a single UPS carrier account 4. Open the saved client (Edit) and go to step 3 Return address 5. Read the hint under STATE again | J34: Client QA-1012-CL01, one carrier account: UPS - QA1012 (SANDBOX) | K34: The hint names the carrier whose limit is being applied. The other fields do this correctly: with only UPS on the client they read 'max 35 chars - UPS', 'max 9 chars - UPS'. | L34: STATE reads 'max 2 chars - USPS' in the new-client wizard and 'max 5 chars - USPS' on the saved client, although that client has no USPS account. Two different limits are attributed to the same carrier, and the carrier named is one the client does not use. | M34: Same page, same field. In the wizard (no carrier staged yet) the limits shown are the strictest across all carriers ('UPS / FEDEX' appears on other fields); on the saved client they narrow to the client's own carriers, and only STATE keeps the USPS label. | N34: http://localhost:5173/settings/clients/QA-1012-CL01 | O34: Always | P34: BUG-033.png, BUG-033-2.png, BUG-033-3.png | R34: admin (ADMIN) | T34: 2026-10-12 | U34: R2 | V34: S040 | X34: Closed | Y34: 2026-10-12 R3: fixed - On a saved client whose only carrier account is UPS the State hint now reads 'max 5 chars - UPS', naming the carrier the limit comes from. In the new-client wizard, before any carrier is staged, it reads 'max 2 chars - USPS', which is the strictest rule across the carriers. The two no longer contradict each other. 2026-10-13 R4 (build local dev, 2026-10-13): fixed - On the saved client QA-1013-CL01, which has a single UPS carrier account, every return-address hint now names UPS and only UPS: 'max 35 chars - UPS' (Attention/Company and Street), 'max 30 chars - UPS' (City), 'max 5 chars - UPS' (State), 'Format: 12345 or 12345-6789 - max 10 chars - UPS' (ZIP), 'max 15 chars - UPS' (Phone). The USPS attribution on a client with no USPS account is gone. The wizard still shows a stricter 'max 2 chars' before any carrier is chosen, which is consistent now that it is the across-all-carriers limit rather than a carrier-specific claim. 2026-10-13 R5 (build local dev, 2026-10-13 (rebuilt after R4; frontend modules dated 13:12 IST)): fixed - Regression check passed on the saved client QA-1013-R5-CL01 (one UPS account): every return-address hint names UPS only - 'max 35 chars - UPS' (Attention, Street, Suite), 'max 30 chars - UPS' (City), 'max 5 chars - UPS' (State), 'Format: 12345 or 12345-6789 - max 10 chars - UPS' (ZIP), 'max 15 chars - UPS' (Phone). | Z34: New
A35: BUG-034 | B35: Low | C35: Validation | D35: Settings | E35: Organization > Clients | F35: Client wizard (Add / Edit) | G35: Markup: kind (Percent / Flat), Value, Currency, Preview, Save markup | H35: Billing markup: a negative or non-numeric value is only refused by the server, as a 'Something went wrong' toast, with nothing marked on the field | I35: 1. Open Settings > Clients, open a client and go to step 6 Markup 2. Choose Percent of rate and type -5 in Value, then click Save markup 3. Replace the value with abc and click Save markup again | J35: Client QA-1012-CL01; markup values -5 and abc | K35: The form refuses a negative or non-numeric percentage as the field is typed, the way the Identity and Return steps do, and the field is marked with the reason. A failed save is not reported as an unexpected error. | L35: Both values are accepted by the field. The live preview simply disappears with no message, Save markup stays active, and the save fails with a red toast headed 'Something went wrong' and the detail 'Value must be a non-negative number.' The field itself is never marked. | M35: The Value input is type=text with no min, max or step. The preview panel vanishing also moves the Save markup button up by about 80 px, so a click aimed at it can land on Next instead (seen during this test). | N35: http://localhost:5173/settings/clients/QA-1012-CL01 | O35: Always | P35: BUG-034.jpg, BUG-034-2.jpg, BUG-034-3.jpg | R35: admin (ADMIN) | T35: 2026-10-12 | U35: R2 | V35: S040 | X35: Closed | Y35: 2026-10-12 R3: fixed - Typing -5 or abc now marks the field at once with 'Value must be a non-negative number.' underneath it. No save attempt and no toast are needed to find out. 2026-10-13 R4 (build local dev, 2026-10-13): fixed - Typing -5 into the markup Value (%) field now marks it red immediately with 'Value must be a non-negative number.' The preview clears and the save never has to be attempted, so the 'Something went wrong' toast no longer appears for an ordinary validation failure. 2026-10-13 R5 (build local dev, 2026-10-13 (rebuilt after R4; frontend modules dated 13:12 IST)): fixed - Typing -5 or abc into the markup Value (%) field marks it at once with 'Value must be a non-negative number.' (aria-invalid true), and clicking Save markup with -5 sends no request. The toast that click raises is still headed 'Something went wrong' - that wording is BUG-036's subject and is recorded there. | Z35: New
A36: BUG-035 | B36: Low | C36: UI | D36: Settings | E36: Organization > Clients | F36: Client wizard (Add / Edit) | G36: Markup: kind (Percent / Flat), Value, Currency, Preview, Save markup | H36: Billing markup preview formats a USD amount with Indian digit grouping: $2,50,00,00,00,024.75 instead of $250,000,000,024.75 | I36: 1. Open Settings > Clients, open a client and go to step 6 Markup 2. Choose Percent of rate, currency USD 3. Type 999999999999 in Value 4. Read the PREVIEW line | J36: Markup: Percent of rate, value 999999999999, currency USD; preview base rate $25.00 | K36: A USD amount is grouped in thousands: $250,000,000,024.75. | L36: The preview reads 'On a $25.00 carrier rate, this markup produces a billable amount of $2,50,00,00,00,024.75.' - lakh/crore grouping. The amount itself is right; only the grouping is wrong. | M36: The number appears to be formatted with the browser's own locale rather than a locale chosen for the currency, so the same screen shows $25.00 (US style) and $2,50,00,00,00,024.75 (Indian style) side by side. Worth checking everywhere money is printed, labels and invoices included. | N36: http://localhost:5173/settings/clients/QA-1012-CL01 | O36: Always | P36: BUG-035.png, BUG-035-2.png, BUG-035-3.png | R36: admin (ADMIN) | T36: 2026-10-12 | U36: R2 | V36: S040 | X36: Closed | Y36: 2026-10-12 R3: fixed - With the value 999999999999 the preview now reads 'a billable amount of $250,000,000,024.75' - thousands grouping, correct for USD. 2026-10-13 R4 (build local dev, 2026-10-13): fixed - A markup of 1000000000% on a $25.00 carrier rate now previews as '$250,000,025.00' - thousands grouping. The lakh/crore grouping is gone. 2026-10-13 R5 (build local dev, 2026-10-13 (rebuilt after R4; frontend modules dated 13:12 IST)): fixed - Regression check passed with the original value: 999999999999 % on a $25.00 rate previews '$250,000,000,024.75' - thousands grouping. (Saving that value then fails with a server 500 - logged separately.) | Z36: New
A37: BUG-036 | B37: Low | C37: Content | D37: Settings | E37: Organization > Clients | F37: Client wizard (Add / Edit) | G37: Edit mode: Cancel and Save changes ('Identity + addresses only') | H37: Edit client: ordinary validation failures are announced as 'Something went wrong', the same red heading the app uses for server errors | I37: 1. Open Settings > Clients and open a client (row menu > Edit) 2. Clear Client name on step 1 Identity 3. Click Save changes 4. Go to step 6 Markup, type -5 in Value and click Save markup | J37: Client QA-1012-CL01; empty Client name; markup value -5 | K37: A field the user has to correct is reported as such ('Fix the highlighted fields to save'), without the heading the app uses when something unexpected has failed. | L37: Both show a red toast headed 'Something went wrong' with the real message underneath: 'Fix the highlighted fields to save.' and 'Value must be a non-negative number.' The same heading was seen on a genuine 502 during the earlier shipment run (BUG-016), so the user cannot tell a typo from an outage. Custom Fields: Save on an empty New field form -> 'Something went wrong - Key and label are both required.'; Type Select with no options -> 'Something went wrong - SELECT fields need comma-separated options.' Output Destinations: Create with no client code -> 'Something went wrong - Client code is required.' Mail: Add provider with no display name -> 'Something went wrong - Kind and display name are required.' Email Templates: Render preview with invalid Variables JSON -> 'Something went wrong - Vars must be valid JSON.' | M37: The on-field message 'Name is required.' is shown correctly at the same time, so only the toast heading is at fault. | N37: http://localhost:5173/settings/clients/QA-1012-CL01 | O37: Always | P37: BUG-036.jpg, BUG-036-2.jpg, BUG-036-3.png, BUG-036-R7-carrier.png, BUG-036-R7-markup.jpg, BUG-036-R7.png | R37: admin (ADMIN) | T37: 2026-10-12 | U37: R2 | V37: S040 | W37: Settings > Organization > Users > Users list; Settings > Carriers & Services > Carrier Accounts; Settings > Carriers & Services > Shipping Catalog; Settings > Labels & Documents > Templates; Settings > Labels & Documents > Custom Fields; Settings > Labels & Documents > Output Destinations; Settings > Email & Alerts > Mail; Settings > Email & Alerts > Email Templates | X37: Reopened | Y37: 2026-10-12 R3: still-failing - Unchanged. Saving the client editor with an empty Client name still raises a red toast headed 'Something went wrong' with 'Fix the highlighted fields to save.' underneath. The field is marked correctly at the same time, and the toast now clears itself (BUG-037), but the heading is still the one used for server failures. 2026-10-13 R4 (build local dev, 2026-10-13): fixed - Editing MKL246 with the email set to 'not-an-email' now marks the field red with the inline message 'Enter a valid email address (name@domain).' and raises a toast headed 'Check the form for errors - Fix the highlighted fields to save.' The 'Something went wrong' heading is no longer used for ordinary validation. MKL246 was left unchanged (email still conac@mkl.com). 2026-10-13 R5 (build local dev, 2026-10-13 (rebuilt after R4; frontend modules dated 13:12 IST)): still-failing - Fixed on Identity, not on Markup. Clearing Client name and clicking Save changes now raises 'Check the form for errors - Fix the highlighted fields to save.' with 'Name is required.' under the field and no request sent. But step 4 of the bug's own steps still fails: on step 6 Markup, typing -5 and clicking Save markup raises a red toast headed 'Something went wrong' with 'Value must be a non-negative number.' beneath - no request is sent, so this is an ordinary validation failure announced with the heading the app uses for server errors. The same heading is used, correctly, a moment later for a real server 500 on the same button, so the two still look alike. Settings > Users has the same fault and is added to the affected screens: Send invite with an empty form raises a red toast headed 'Something went wrong' with 'Email and client are required.' underneath, and no request is sent. Settings > Carrier Accounts has it too: Save to Account Book with required fields empty, or with a 41+ character name, raises 'Something went wrong - Please fix the highlighted fields before saving.' while the fields themselves are marked correctly ('Account number is required', 'Max 40 characters'), with no request sent. Shipping Catalog > Add Package too: 'Something went wrong - Give the package a name.' and 'Something went wrong - A custom box needs length, width and height.', with no field marked and no request sent. Templates too: a 352 KB logo is refused with 'Something went wrong - Logo must be under 200 KB. Try compressing the image.' 2026-10-14 R6 (build local dev, 2026-10-14 (order-form modules reloaded 13:17 IST)): still-failing - R6: still failing. Carrier Accounts > Add carrier account, Save with required fields empty: 'Something went wrong - Please fix the highlighted fields before saving.' with the fields marked and no request sent. Output Destinations > Create with no client code: 'Something went wrong - Client code is required.', no request sent. The client wizard's Markup step (the bug's own steps) could not be re-walked: the client editor did not compile during this run (ClientEditorPage.tsx parse error). 2026-10-16 R7 (build local dev, 2026-10-16): still-failing - R7: fixed on the bug's own screen, still failing everywhere else it lists. Client editor > step 6 Markup, Value -5, Save markup: the toast is now headed 'Check the form for errors' with 'Value must be a non-negative number.' underneath, and no request is sent (the same sentence is also shown under the field). Still headed 'Something went wrong' for ordinary validation failures: Settings > Users > Invite user with an empty form ('Email and client are required.', no request sent); Settings > Carrier Accounts > Add Account > Save to Account Book with the required fields empty ('Please fix the highlighted fields before saving.' while the fields are marked, no request sent); Settings > Mail > Add provider with no display name. The scanner enrolment and the Markup step show the corrected heading, so the fix reached those screens only. | Z37: Fixed | AB37: Fix landed earlier this session: Markup validation heading shipped as 9b7cb64d earlier this session. | AC37: 2026-10-15
A38: BUG-037 | B38: Low | C38: Usability | D38: Settings | E38: Organization > Clients | F38: Clients list | G38: Toasts and messages (success, validation, server errors) | H38: Error toasts never time out: a failed-delete message was still on screen 38 minutes later, through navigation and other work | I38: 1. Open Settings > Clients (/settings/clients) 2. Scroll the table right, open the row menu on MKL246 and click Delete (it is refused because the client has orders) 3. Carry on working: open other Settings steps, edit a client, come back 4. Look at the bottom right of the window | J38: Toast 'Something went wrong - MKL246 has 404 pending order(s). Complete or void them before deleting.' raised at 09:37, still shown at 10:15 | K38: An error message disappears on its own after a short time, like the green 'Done' toasts, or at the latest when the user moves to another screen. | L38: Red toasts stay until clicked away. They survive moving between wizard steps and back to the list, and they stack: three were on screen at once earlier in this run. Each one covers the bottom-right corner of the page. | M38: Green success toasts ('Markup saved for QA-1012-CL01.') do disappear by themselves, so only the error ones are affected. A 'Dismiss all' button appears once more than one is open. | N38: http://localhost:5173/settings/clients | O38: Always | P38: BUG-037.jpg | R38: admin (ADMIN) | T38: 2026-10-12 | U38: R2 | V38: S006 | X38: Closed | Y38: 2026-10-12 R3: fixed - The refusal toast for deleting MKL246 now carries a countdown bar and cleared itself within about 10 seconds without being clicked. 2026-10-13 R4 (build local dev, 2026-10-13): fixed - The error toast from that failed save had dismissed itself within 15 seconds. It no longer persists across navigation. 2026-10-13 R5 (build local dev, 2026-10-13 (rebuilt after R4; frontend modules dated 13:12 IST)): fixed - Regression check passed: the two red toasts raised on the Markup step ('Something went wrong - Value must be a non-negative number.' and the server-error one with reference 3e0a8978) had both dismissed themselves within about 20 seconds; only the later green 'Done - Markup saved' toast remained. | Z38: New
A39: BUG-038 | C39: Query | D39: Settings | E39: Organization > Clients | F39: Clients list | G39: Export (CSV of current view) | H39: Clients Export: the button promises 'visible columns, filtered rows' but the request carries no column information, so hidden columns are unlikely to be left out | I39: 1. Open Settings > Clients (/settings/clients) 2. Hover over Export and read the tooltip 3. Click Export and look at the request the page sends 4. Type THB in the search box and click Export again 5. Hide the Contact column from the Columns menu and click Export again | J39: 3 clients; search THB; Contact column hidden | K39: Either the CSV matches the view as the tooltip says, or the tooltip only promises what the export really does. | L39: The tooltip reads 'Export the current view as CSV - visible columns, filtered rows'. Rows are honoured: the request becomes /api/v1/clients/export.csv?sortBy=code&sortDirection=ASC&search=THB. Columns are not sent at all - the request is identical with the Contact column hidden - so the server cannot know which columns to leave out. | M39: Requests seen on Clients: .../export.csv?sortBy=code&sortDirection=ASC and .../export.csv?sortBy=code&sortDirection=ASC&search=THB, both 200. The downloaded file itself could not be opened from this session, so the CSV content is not verified - please confirm with a file. The same button on Settings > Warehouses behaves differently: no server call at all, the file is built in the page and fetched from a data: URL, so the two lists do not share an export path even though the tooltip is identical. | N39: http://localhost:5173/settings/clients | O39: Always | P39: Not captured | R39: admin (ADMIN) | T39: 2026-10-12 | U39: R2 | V39: S006 | X39: Closed | Y39: 2026-10-12 R3: cannot-retest - The implementation has changed: the Clients Export no longer calls /api/v1/clients/export.csv at all. Like the Warehouses one it now builds the file in the page and fetches it from a data: URL, so the original evidence - that no column information was sent to the server - no longer applies, and a client-side build can honour the hidden columns. The file itself still cannot be opened from this session, so whether the CSV matches the visible columns is still unverified. 2026-10-13 R4 (build local dev, 2026-10-13): still-failing - Now reproducible and confirmed failing. With six of the seven columns hidden and the search set to THB, Export sent GET /api/v1/clients/export.csv?sortBy=code&sortDirection=ASC&search=THB. The filter is carried, but there is no column parameter of any kind, so the 'visible columns' half of the button's promise is not honoured - the file will contain every column regardless of what is on screen. 2026-10-13 R5 (build local dev, 2026-10-13 (rebuilt after R4; frontend modules dated 13:12 IST)): still-failing - Half fixed. The page now sends the visible columns and the server drops the hidden ones - with Contact and Orders hidden and THB in the search box, Export (download permitted by Manoj) sent GET /api/v1/clients/export.csv?sortBy=orderCount&sortDirection=DESC&search=THB&columns=code,name,country,accounts,status,actions and the CSV read in the page was 'Code,Name,Country,Carrier accounts,Status' / 'THB000,Thoroughbred Fulfillment LLC,US,,ACTIVE'. But the server never writes Contact or Orders, even when they are visible and requested: with the default layout (all seven columns shown) the request is ...&columns=code,name,contact,country,accounts,orderCount,status,actions and the file still has only 'Code,Name,Country,Carrier accounts,Status'. So a user who can see Contact and Orders on screen gets a file without them - the 'visible columns' promise is still not kept, now in the other direction. Likely the server does not recognise the ids 'contact' and 'orderCount'. 2026-10-14 R6 (build local dev, 2026-10-14 (order-form modules reloaded 13:17 IST)): still-failing - R6: unchanged since R5. Export now sends the visible columns (columns=code,name,contact,country,accounts,orderCount,status,actions), but the CSV the server returns still has only 'Code,Name,Country,Carrier accounts,Status' - Contact and Orders are never written, even when they are shown. Checked with the download caught in the page. 2026-10-16 R7 (build local dev, 2026-10-16): fixed - R7: with the default layout Export sends columns=code,name,contact,country,accounts,orderCount,status,actions and the CSV header is now 'Code,Name,Email,Phone,Country,Carrier accounts,Orders,Status' - Contact (as Email + Phone) and Orders are written. With Contact and Orders hidden the file is 'Code,Name,Country,Carrier accounts,Status'. CSV read from the download caught in the page; layout reset afterwards. | Z39: Fixed | AB39: Fixed on dev (9681f4ff): FE columns (contact/orderCount/actions) now alias to backend map keys so CSV contains the right columns. | AC39: 2026-10-15
A40: BUG-039 | B40: Low | C40: UI | D40: Settings | E40: Organization > Clients | F40: Client wizard (Add / Edit) | G40: Breadcrumb and browser tab title in the wizard | H40: Client wizard: the top breadcrumb still reads 'Settings' and the browser tab is always 'multiship-react', so neither says which client is open | I40: 1. Open Settings > Clients and click + Add Client (/settings/clients/new) 2. Look at the breadcrumb in the top bar and at the browser tab title 3. Open an existing client with the row menu > Edit (/settings/clients/MKL246) and look again | J40: Pages /settings/clients, /settings/clients/new and /settings/clients/MKL246 | K40: The breadcrumb follows the page, as it does on the list itself ('Settings > Clients'), and the tab title names the screen and the record, so a user with several tabs open can tell them apart and a bookmark is meaningful. | L40: On both wizard pages the breadcrumb shows only 'Settings', losing the 'Clients' step and the client, even though the page header shows 'EDIT CLIENT - MKL (MKL246)'. The browser tab reads 'multiship-react' on every page in the application. | M40: document.title is 'multiship-react' on /settings/clients, /settings/clients/new and /settings/clients/MKL246. | N40: http://localhost:5173/settings/clients/new | O40: Always | P40: BUG-039.jpg | R40: admin (ADMIN) | T40: 2026-10-12 | U40: R2 | V40: S040 | X40: Closed | Y40: 2026-10-12 R3: still-failing - Half fixed. The browser tab title is now 'New client - Settings' instead of 'multiship-react'. The breadcrumb in the top bar still reads only 'Settings' on /settings/clients/new and on a client's edit page, losing both the Clients step and the client itself. 2026-10-13 R4 (build local dev, 2026-10-13): fixed - The browser tab now reads 'New client - Settings' instead of 'multiship-react', and the panel header reads 'NEW CLIENT / Register a client'. The global breadcrumb reads 'SETTINGS ... Clients', naming the section the wizard belongs to rather than just 'Settings'. 2026-10-13 R5 (build local dev, 2026-10-13 (rebuilt after R4; frontend modules dated 13:12 IST)): fixed - Regression check passed: on /settings/clients/new the browser tab reads 'New client - Settings' and the top breadcrumb 'SETTINGS > Clients'. | Z40: New
A41: BUG-040 | B41: Medium | C41: Validation | D41: Settings | E41: Organization > Warehouses | F41: Warehouses list | G41: Add / Edit warehouse panel: address fields and country | H41: Add warehouse accepts a state of 'ILLINOIS' and a 10-character postal code, although this is the ship-from address printed on every label | I41: 1. Open Settings > Warehouses and click + Add Warehouse 2. Fill Code QA-1012-WH01 and a name 3. Line 1 742 Evergreen Terrace, City Springfield 4. State / region: type ILLINOIS 5. Postal code: type 62704-1234 6. Phone +1 (217) 555-0100, Country US 7. Click Create warehouse | J41: Warehouse QA-1012-WH01, state ILLINOIS, postal code 62704-1234, country US | K41: The ship-from address is checked at least as strictly as the client's return address, which caps State at 2 characters for a US address and checks the postal code format. UPS and FedEx both need a 2-letter state code for US addresses, so 'ILLINOIS' will be refused at label time. | L41: No check at all. State / region accepts up to 50 characters with no format rule and no carrier hint, Postal code accepts up to 20 with no format rule. The warehouse saves and the list shows 'Springfield, ILLINOIS'. The same window on the client Return address step would have truncated both and shown an error. | M41: Input maxlengths on this panel: Code 50, Name 255, Line 1 255, Line 2 255, City 100, State 50, Postal code 20, Country 2, Phone 50. No per-carrier hints are shown, unlike the Return address step which shows 'max 2 chars - USPS', 'Format: 12345 or 12345-6789' and so on. Required fields are checked ('State / region is required.'), so only the content rules are missing. | N41: http://localhost:5173/settings/warehouses | O41: Always | P41: BUG-040.jpg, BUG-040-2.jpg | R41: admin (ADMIN) | T41: 2026-10-12 | U41: R2 | V41: S007 | X41: Closed | Y41: 2026-10-12 R3: fixed - Add warehouse now refuses the carrier-breaking values. Typing ILLINOIS into State / region marks the field 'State / region must be 2 characters or fewer.'; typing NOTAZIPCODE12345678 into Postal code marks it 'Postal code must be 10 characters or fewer.' Create warehouse greys out while either is wrong. The rules are length rules rather than format rules - a 2-character non-state such as XX is still accepted - but the values that broke the carriers are now rejected before the record is saved. 2026-10-13 R4 (build local dev, 2026-10-13): fixed - Re-walked. ILLINOIS in State / region is marked 'State / region must be 2 characters or fewer.'; NOTAZIPCODE12345678 is marked 'Postal code must be 10 characters or fewer.' Clicking Create warehouse with those values sends no request at all and raises 'Missing details - Fix the highlighted fields before saving.' with every failing field marked, Street address included. 2026-10-13 R5 (build local dev, 2026-10-13 (rebuilt after R4; frontend modules dated 13:12 IST)): fixed - Regression check passed: Add warehouse QA-1013-R5-WH01 with State / region ILLINOIS marks the field 'State / region must be 2 characters or fewer.'; Create warehouse then sends no request and raises 'Missing details - Fix the highlighted fields before saving.' The ZIP+4 62704-1234 is accepted. (A lower-case 'il' is accepted and stored as typed - added to BUG-079.) | Z41: New
A42: BUG-041 | B42: Medium | C42: Functional | D42: Settings | E42: Organization > Warehouses | F42: Warehouses list | G42: Row menu > Attach clients | H42: Warehouses > Attach clients: the dialog never shows which clients are already attached, and nothing on the screen can detach one | I42: 1. Open Settings > Warehouses 2. Scroll the table right, open the row menu on a warehouse and click Attach clients 3. Tick a client and click Attach - the Attached count goes up and 'Attached QA-1012-WH01 to 1 client.' is shown 4. Open the same row menu > Attach clients again 5. Look for a way to undo the attachment anywhere on this screen | J42: Warehouse QA-1012-WH01 attached to client THB000 | K42: The dialog shows the clients already attached, ticked or marked, so the user can see the current state; and an attachment made by mistake can be undone from the same place. | L42: Both clients are shown unticked every time, with no sign that THB000 is attached - the only clue is the Attached count in the grid. The subtitle says 'Existing attachments are unaffected', so the dialog only ever adds. The row menu offers Attach clients, Edit and Delete only, and the Edit panel does not list attachments either, so an attachment can be created here but never removed. | M42: Ticking a client also reveals 'Set as this client's default warehouse', which silently changes that client's default - another reason the current state needs to be visible. The only way found to change it is the client's own Ship From step. | N42: http://localhost:5173/settings/warehouses | O42: Always | P42: BUG-041.jpg, BUG-041-2.jpg, BUG-041-3.png | R42: admin (ADMIN) | T42: 2026-10-12 | U42: R2 | V42: S007 | X42: Closed | Y42: 2026-10-12 R3: fixed - Row menu > Attach clients on a warehouse with one attached client: the dialog subtitle now reads 'Pick clients to attach. Rows already attached carry a badge + Detach button.', THB000 shows a green ATTACHED badge and a red Detach button. Detach opens 'Detach client - Detach THB000 from warehouse QA-1012-WH02?' and on confirm the badge clears and a 'Detached THB000.' toast appears. Re-attach works too. Retested on QA-1012-WH02 at 1392x847. 2026-10-13 R4 (build local dev, 2026-10-13): fixed - Row menu > Attach clients on QA-1013-WH01 shows the subtitle 'Pick clients to attach. Rows already attached carry a badge + Detach button.' with QA-1013-CL01 carrying a green ATTACHED badge and a red Detach button. 2026-10-13 R5 (build local dev, 2026-10-13 (rebuilt after R4; frontend modules dated 13:12 IST)): fixed - Regression check passed: row menu > Attach clients on 3PL-EAST lists MKL246, QA-1013-R5-CL01 and THB000 each with an ATTACHED badge and a red Detach button. Detach on my own QA-1013-R5-CL01 asks 'Detach client - Detach QA-1013-R5-CL01 from warehouse 3PL-EAST?' (in-app Cancel / Detach) and removes it; ticking it again with 'Set as this client's default warehouse' re-attaches it ('Attached 3PL-EAST to 1 client (default).'). Note that the grid's Attached count disagrees with this list (BUG-080). | Z42: New
A43: BUG-042 | B43: Low | C43: Content | D43: Settings | E43: Organization > Warehouses | F43: Warehouses list | G43: Add / Edit warehouse panel: carrier address Verify | H43: Warehouse address Verify reports the raw status NOT_SUPPORTED, and the green tick icon makes a refusal look like a pass | I43: 1. Open Settings > Warehouses, open a warehouse with the row menu > Edit 2. Next to ADDRESS pick carrier UPS and click Verify 3. Repeat with FEDEX and with USPS | J43: Warehouse QA-1012-WH01, 742 Evergreen Terrace, Springfield, ILLINOIS, 62704-1234, US; carriers UPS, FEDEX, USPS | K43: The result is written for the user, and an address that was not checked does not carry a success tick. | L43: Each result line reads '<CARRIER> - NOT_SUPPORTED' with a green circled-tick icon in front of it. UPS and FedEx add 'No live credentials for <carrier> - cannot call address validation.'; USPS adds 'SERA address validation needs live credentials; the account is on a fallback token.' The explanations are clear, but the raw enum and the tick icon together read as though the address passed. | M43: POST /api/v1/addresses/validate/carrier -> 200 for each of the three carriers; no carrier was actually contacted, because the sandbox accounts have no live address-validation credentials. The address itself (state 'ILLINOIS') therefore went unchecked - see BUG-040. Each result has its own Dismiss link. | N43: http://localhost:5173/settings/warehouses | O43: Always | P43: BUG-042.jpg | R43: admin (ADMIN) | T43: 2026-10-12 | U43: R2 | V43: S007 | X43: Closed | Y43: 2026-10-12 R3: fixed - The Verify result now reads 'UPS - VERIFICATION NOT SUPPORTED FOR THIS COUNTRY' with the explanation 'No live credentials for UPS - cannot call address validation.' and a Dismiss action, behind a neutral blue info icon. The raw NOT_SUPPORTED status and the green tick that made a refusal look like a pass are both gone. 2026-10-13 R4 (build local dev, 2026-10-13): fixed - Verify on a US address with no live UPS credentials returns 'UPS - VERIFICATION NOT SUPPORTED FOR THIS COUNTRY / No live credentials for UPS - cannot call address validation. / Dismiss', behind a neutral info icon. No raw NOT_SUPPORTED and no green tick on a refusal. 2026-10-13 R5 (build local dev, 2026-10-13 (rebuilt after R4; frontend modules dated 13:12 IST)): fixed - Regression check passed in substance: Verify with carrier UPS on the new warehouse returns 'UPS - VERIFICATION NOT SUPPORTED FOR THIS COUNTRY / No live credentials for UPS - cannot call address validation. / Dismiss' behind a neutral info icon - no raw NOT_SUPPORTED and no green tick. The headline itself is inaccurate for a US address (the cause is the credentials, not the country) - logged separately. | Z43: New
A44: BUG-043 | B44: Medium | C44: Usability | D44: Settings | E44: Organization > Warehouses | F44: Warehouses list | G44: Status toggle (Activate / Deactivate warehouse) | H44: Deactivating a warehouse that clients ship from happens on one click, with no warning - the same action on a client asks first and lists the cascade | I44: 1. Open Settings > Warehouses 2. Pick a warehouse with a number greater than 0 in the Attached column 3. Click its Status toggle | J44: Warehouse QA-1012-WH01, Attached = 1 (client THB000) | K44: The same care as on the Clients screen, where Deactivate asks 'Deactivate QA-1012-CL01?' and lists what else it will disable. The panel's own wording - 'inactive warehouses are hidden from shipment resolution' - means this can stop a client shipping. | L44: One click and it is done: the row turns Inactive and a green toast says 'QA-1012-WH01 is now inactive.' Nothing is asked, and the attached clients are not mentioned even though the Attached column shows 1. | M44: Re-activating is also a single click. The toast prints the status in lower case here ('is now inactive.') and in upper case on the Clients screen ('is now ACTIVE.'). | N44: http://localhost:5173/settings/warehouses | O44: Always | P44: BUG-043.jpg, BUG-043-2.jpg, BUG-043-3.png | R44: admin (ADMIN) | T44: 2026-10-12 | U44: R2 | V44: S007 | X44: Closed | Y44: 2026-10-12 R3: fixed - Toggling the Status switch off on QA-1012-WH02 (1 client attached) now opens 'Deactivate warehouse - Deactivate warehouse QA-1012-WH02? It is currently attached to 1 client - any shipment that resolves ship-from to this warehouse will error until it is reactivated.' with Cancel / Deactivate; only on confirm does the row go Inactive. Delete likewise warns 'It is currently attached to 1 client - they will be unlinked.' 2026-10-13 R4 (build local dev, 2026-10-13): fixed - Toggling QA-1013-WH01 off with one client attached raises 'Deactivate warehouse - Deactivate warehouse QA-1013-WH01? It is currently attached to 1 client - any shipment that resolves ship-from to this warehouse will error until it is reactivated.' with Cancel / Deactivate. 2026-10-13 R5 (build local dev, 2026-10-13 (rebuilt after R4; frontend modules dated 13:12 IST)): fixed - Regression check passed: the Status toggle on QA-1013-R5-WH01 (attached to 1 client) raises 'Deactivate warehouse - Deactivate warehouse QA-1013-R5-WH01? It is currently attached to 1 client - any shipment that resolves ship-from to this warehouse will error until it is reactivated.' Cancel leaves it Active, Deactivate sets Inactive, re-activating is immediate. | Z44: New
A45: BUG-044 | B45: High | C45: Functional | D45: Settings | E45: Organization > Address book | F45: Address book list | G45: Page header and list load | H45: Settings > Address book never loads: its only data call returns 500 every time, and the page shows the 'No saved addresses yet' empty state as though the book were empty | I45: 1. Open Settings > Address book (/settings/address-book) 2. Wait for the page to settle and read the two red toasts 3. Click Refresh at the top right 4. Watch the request the page makes | J45: No test data needed - the failure is on page load | K45: The saved addresses are listed, or, if the call fails, the grid says the list could not be loaded and offers a retry - not a message that says there are none. | L45: GET /api/v1/recipients?page=0&size=25 returns 500 on every attempt. The grid shows 'No saved addresses yet. Add one here, or use "Save to address book" in Ship to on a new shipment.' On the first load two red toasts appear ('Something went wrong on the server... contact support with reference 4afd47af'), but on Refresh the call fails again with no message at all, so the page quietly claims the address book is empty. There is no way to tell from the screen whether there are no addresses or whether the list failed to load. | M45: Every read of the address book fails and every failure is drawn as an empty state. GET /api/v1/recipients?page 0&size 25 -> 500 (twice on load, twice on Refresh - the page calls it twice each time). The search sends GET /api/v1/recipients?q QA-1012&page 0&size 25 -> 502 and the grid reads 'No saved addresses match "QA-1012".' The client filter sends GET /api/v1/recipients?customerNo MKL246&page 0&size 25 -> 502 and the grid reads 'No saved addresses yet.' First-load toast text: 'Something went wrong on the server. Please try again in a moment. If this keeps happening, contact support with reference 4afd47af.' Further references seen: 51350c06, 9da70cce. No browser console errors. The whole screen is unusable, so none of its controls could be checked against real rows. | N45: http://localhost:5173/settings/address-book | O45: Always | P45: BUG-044.jpg, BUG-044-2.jpg | R45: admin (ADMIN) | T45: 2026-10-12 | U45: R2 | V45: S008 | X45: Closed | Y45: 2026-10-12 R3: fixed - GET /api/v1/recipients?page=0&size=25 now returns 200 and the grid lists the saved addresses with a '1 saved address' / '2 saved addresses' count. Search (?q=Bremner, ?q=60601, ?q=zzz) and the client filter all return 200 as well. 2026-10-13 R4 (build local dev, 2026-10-13): fixed - Settings > Address book loads. GET /api/v1/recipients?page=0&size=25 returns 200, the grid renders, and the empty state shown is now truthful rather than a disguised failure. 2026-10-13 R5 (build local dev, 2026-10-13 (rebuilt after R4; frontend modules dated 13:12 IST)): fixed - Regression check passed: Settings > Address book loads - GET /api/v1/recipients?page=0&size=25 -> 200 (twice, StrictMode) - and the empty state 'No saved addresses yet...' is now the truth (there were none). After adding one, the row and the count line '1 saved address' appear. | Z45: New
A46: BUG-045 | B46: High | C46: Data integrity | D46: Settings | E46: Organization > Address book | F46: Address book list | G46: Add / Edit address form | H46: Address book: a saved address is reported as a server failure, because the list reload that follows the save is what actually fails | I46: 1. Open Settings > Address book (/settings/address-book) 2. Click + Add address 3. Fill Name QA-1012 Test Recipient, Street 290 Bremner Blvd, City Chicago, State IL, Postal code 60601, Country United States 4. Click Save address 5. Read the toast and the grid | J46: Shared address 'QA-1012 Test Recipient', 290 Bremner Blvd, Chicago, IL 60601, US | K46: A save that succeeded is reported as a success. If the list cannot be reloaded afterwards, that is reported separately and does not cast doubt on the save. | L46: POST /api/v1/recipients returns 200 - the address is created - but the dialog closes onto a red 'Something went wrong on the server... contact support with reference 9da70cce' and the grid still reads 'No saved addresses yet'. Everything on screen says the save failed. The failure is really the GET that follows it (BUG-044). A user will save again, and again, each time creating another copy they cannot see. | M46: POST /api/v1/recipients -> 200, then GET /api/v1/recipients?page 0&size 25 -> 500. One address was created during this test and cannot be seen or deleted from the UI while the list call fails: 'QA-1012 Test Recipient', shared with every client. | N46: http://localhost:5173/settings/address-book | O46: Always | P46: BUG-045.jpg | R46: admin (ADMIN) | T46: 2026-10-12 | U46: R2 | V46: S008 | X46: Closed | Y46: 2026-10-12 R3: fixed - A new shared address (QA-1012 Retest Recipient, 1 Retest Way, Chicago IL 60601) saved cleanly: POST /api/v1/recipients 200, the dialog closed with no error toast and the row appeared at once. The earlier false failure was the broken reload, which is fixed with BUG-044. 2026-10-13 R4 (build local dev, 2026-10-13): fixed - Saving 'QA-1013 Test Recipient, 742 Evergreen Terrace, Springfield IL 62704 US' sent POST /api/v1/recipients -> 200 followed by GET /api/v1/recipients?page=0&size=25 -> 200. The dialog closed, the row appeared in the grid and the count read '1 saved address'. No false 'Something went wrong on the server' toast, so no risk of duplicate saves. 2026-10-13 R5 (build local dev, 2026-10-13 (rebuilt after R4; frontend modules dated 13:12 IST)): fixed - Regression check passed: saving a new shared address sent POST /api/v1/recipients -> 200 ('Recipient saved.') and the dialog closed onto the new row with '1 saved address'; no false server-error toast. Editing it (PUT /recipients/4 -> 200) reported 'Updated QA-1013-R5 Retest Recipient.' | Z46: New
A47: BUG-046 | C47: Query | D47: Settings | E47: Organization > Clients | F47: Client wizard (Add / Edit) | G47: Defaults > Origin country | H47: Country lists differ across Settings: the client's default Origin country offers 12 countries, the address book offers 250 | I47: 1. Open Settings > Clients > + Add Client and open the Defaults > Origin country list on step 1 2. Open Settings > Address book > + Add address and open the Country list | J47: No data needed - the two lists are compared as shown | K47: One country list, taken from Settings > Countries, so a client whose goods originate outside those 12 can be set up, and the two screens agree. | L47: Origin country on the client wizard has 13 entries: '- none -' plus US, CA, MX, GB, DE, FR, IN, CN, AU, JP, AE, SG. The address book Country list has 250. The warehouse panel takes a free-typed ISO-2 code instead, with no list at all - three different approaches to the same field in one settings area. | M47: Counted from the select options on each screen. Whether the 12 are a deliberate shortlist of supported origins is the question - if so it is worth saying so on the field, since a client with an origin outside the list cannot be set up at all. | N47: http://localhost:5173/settings/clients/new | O47: Always | P47: BUG-046-R7-warehouse.png, BUG-046-R7-wizard.png | R47: admin (ADMIN) | T47: 2026-10-12 | U47: R2 | V47: S040 | X47: Closed | Y47: 2026-10-12 R3: still-failing - Unchanged. Defaults > Origin country still offers 13 options (none plus 12 countries) while the address book Country list still offers 250. 2026-10-13 R4 (build local dev, 2026-10-13): still-failing - Unchanged - the same field is still built three different ways inside Settings. The Add warehouse panel takes COUNTRY (ISO-2) as a free-typed text box with no list; the address book Add address dialog offers a 250-entry country select; the client wizard's Origin country is a searchable combobox. A code typed into the warehouse box is not checked against any list. 2026-10-13 R5 (build local dev, 2026-10-13 (rebuilt after R4; frontend modules dated 13:12 IST)): still-failing - Narrowed, not solved: the same field is now built two ways instead of three. The warehouse panel (Settings > Warehouses > Add warehouse) and the client wizard's Origin country both use the shared searchable country list, which holds 50 countries (US, CA, MX, GB, IE ... BR, AR, CL, CO, PE) - 'Iceland' gives 'No match' in both. The address book's Add address dialog still has its own native select with 250 countries, Iceland included, although the fix comment says it uses the shared one. So a client whose goods originate in, or a warehouse located in, one of the 200 missing countries still cannot be set up, while the address book offers them. 2026-10-14 R6 (build local dev, 2026-10-14 (order-form modules reloaded 13:17 IST)): still-failing - R6: unchanged since R5. Warehouses > Add warehouse still uses the short searchable list ('Icel' -> 'No match', 'Peru' found), while Address book > Add address has its own select with 250 countries (Iceland and Peru included), and Importer / Broker's importer Country is another long select. The client wizard's Origin country could not be opened (client editor down). 2026-10-16 R7 (build local dev, 2026-10-16): fixed - R7: one 250-country list on every screen the bug compares. Client editor > Defaults > Origin country: the searchable list holds 250 entries (United States, Canada, Mexico ... U.S. Minor Outlying Islands) and 'Icel' finds Iceland (IS), which gave 'No match' in R5/R6. Settings > Warehouses > Add warehouse (Country) and Settings > Address book > Add address use the same full list, and the importer Country on Settings > Importer / Broker is a 250-option select too. | Z47: Fixed | AB47: Fixed on dev (bf6e96b8): Warehouse Country swaps the free-text ISO-2 input for the shared CountrySelect used by /orders/new + address book + client wizard. R6+1 (e17bf946, 2026-10-15): _countryData.ts sources from utils/countries.ts; CountrySelect now exposes the full 250-country list. Address book dialog switched to CountrySelect so warehouse / client / address book agree. | AC47: 2026-10-15
A48: BUG-047 | B48: Low | C48: Performance | D48: Settings | E48: Organization > Users | F48: Users list | G48: Search username, email, name | H48: Users search is not debounced: every keystroke sends a search request and a second request that reloads the audit list | I48: 1. Open Settings > Users (/settings/users) 2. Type manoj into 'Search username, email, name...' at a normal typing speed 3. Watch the requests the page sends | J48: Search term 'manoj' (5 characters) | K48: The search waits for a pause before asking the server, the way the Clients and Warehouses lists do - one request per settled term. | L48: Ten requests for five characters: GET /api/v1/admin/users?search=m, ...search=ma, ...search=man and so on, each followed by GET /api/v1/admin/users/audit?limit=50. The audit list has nothing to do with the search term and is reloaded every time. | M48: 53 requests were captured over a short search session on this screen. The Clients list sends one request per settled term for the same kind of search box, so the two behave differently. | N48: http://localhost:5173/settings/users | O48: Always | P48: Not captured | R48: admin (ADMIN) | T48: 2026-10-12 | U48: R2 | V48: S009 | X48: Closed | Y48: 2026-10-12 R3: fixed - Typing 'manoj' (5 characters) at normal speed into the user search now sends exactly one request - GET /api/v1/admin/users?search=manoj&page=0&size=50 - with a single accompanying GET /api/v1/admin/users/audit?limit=50, instead of ten requests. A clear (x) button has also been added to the search box. 2026-10-13 R4 (build local dev, 2026-10-13): fixed - Typing 'manoj' into the user search sends exactly one request, GET /api/v1/admin/users?search=manoj&page=0&size=50, with a single accompanying audit reload. The ten-requests-for-five-keystrokes behaviour is gone. 2026-10-13 R5 (build local dev, 2026-10-13 (rebuilt after R4; frontend modules dated 13:12 IST)): fixed - Typing 'manoj' at normal speed into 'Search username, email, name...' sent one search, GET /api/v1/admin/users?search=manoj&page=0&size=50 -> 200, with a single audit reload, and listed only manoj7000. Matching stays case-insensitive: 'SUYOGINDIA' finds manoj7000 by email. | Z48: New
A49: BUG-048 | B49: Low | C49: Content | D49: Settings | E49: Organization > Users | F49: Users list | G49: Invite user form (fields, validation, send) | H49: Invite user: a bad email address is reported under the heading 'This shipment needs attention', with the raw field message repeated underneath | I49: 1. Open Settings > Users (/settings/users) 2. Click Invite user 3. Type not-an-email in Email and pick client THB000 4. Click Send invite | J49: Email 'not-an-email', client THB000, role USER | K49: A message about the user being invited, shown once, in words: for example 'Enter a valid email address'. Nothing about shipments. | L49: A red toast headed 'This shipment needs attention' with two lines: 'Email must be a well-formed email address.' and 'email - must be a well-formed email address'. The heading belongs to the shipment screens, and the second line is the raw field-and-message pair repeated. | M49: No request is sent, so the check is in the page. The same dialog with an empty form shows a third heading, 'Something went wrong - Email and client are required.' - so one small form produces three different heading styles, none of which marks the field itself. | N49: http://localhost:5173/settings/users | O49: Always | P49: BUG-048.jpg, BUG-048-2.jpg, BUG-048-3.png, BUG-048-4.jpg, BUG-048-5.jpg, BUG-048-6.png, BUG-048-7.png | R49: admin (ADMIN) | T49: 2026-10-12 | U49: R2 | V49: S009 | X49: Closed | Y49: 2026-10-12 R3: still-failing - Half fixed. The heading is corrected - the toast now reads 'Check the form for errors' instead of 'This shipment needs attention'. The duplication remains: the toast still prints the message twice, once in words ('Email must be a well-formed email address.') and once as the raw field-and-message pair ('email - must be a well-formed email address'). Retested with not-an-email + client THB000 + role USER. 2026-10-13 R4 (build local dev, 2026-10-13): fixed - Submitting the Invite user form with 'not-an-email' now raises a single toast: 'Check the form for errors - Email must be a well-formed email address.' Both halves of the original finding are resolved - the shipment heading is gone and the duplicated raw field-and-message line is gone. 2026-10-13 R5 (build local dev, 2026-10-13 (rebuilt after R4; frontend modules dated 13:12 IST)): fixed - Send invite with 'not-an-email' and client QA-1013-R5-CL01 sent POST /api/v1/admin/user-invites -> 400 and raised one toast: 'Check the form for errors - Email must be a well-formed email address.' No shipment heading and no repeated raw field line. A 273-character address is refused with the same message. | Z49: New
A50: BUG-049 | B50: Low | C50: Content | D50: Settings | E50: Organization > Users | F50: Users list | G50: Page header and description | H50: Internal developer notes are printed in the page descriptions users read: sprint numbers, database column names and a to-do | I50: 1. Open Settings > Users (/settings/users) and read the page description and the panel description 2. Open Settings > Mail (/settings/mail) and read the page description 3. Open Settings > Roles (/settings/roles) and read the page description | J50: No data needed - the text is part of the page | K50: The description tells the user what the screen is for. Sprint numbers, column names and internal to-dos belong in the backlog. | L50: Users, page description: 'Assign each USER account to a client, deactivate revoked accounts, and audit the changes. Backfill client_code before flipping the tenant-scope flag.' Users, panel description: '...Sprint 50 rollout: every legacy USER should be assigned a client before the tenant-scope flag is flipped.' Mail, page description: '...pick SMTP today (SendGrid/SES/Postmark coming), edit host/port/creds, and send a live test message. Config lives in mail_provider + mail_config.' Roles, page description: 'Platform-wide role registry. Read-only; add roles via SQL today.' | M50: 'client_code', 'mail_provider' and 'mail_config' are database identifiers; 'Sprint 50 rollout' and 'SendGrid/SES/Postmark coming' are roadmap notes. Other Settings pages are written for the user ('Customer master data - who you ship for, their carrier accounts, and defaults.'), so this is not the house style. | N50: http://localhost:5173/settings/users | O50: Always | P50: BUG-049.jpg, BUG-049-2.jpg, BUG-049-3.png, BUG-049-4.jpg, BUG-049-5.jpg, BUG-049-6.png, BUG-049-7.png | R50: admin (ADMIN) | T50: 2026-10-12 | U50: R2 | V50: S009 | W50: Settings > Email & Alerts > Mail; Settings > Organization > Roles > Roles list | X50: Closed | Y50: 2026-10-12 R3: still-failing - Only the Users panel description was cleaned (the 'Sprint 50 rollout...' sentence is gone). The three page descriptions are unchanged: Users still ends 'Backfill client_code before flipping the tenant-scope flag.', Mail still ends 'Config lives in mail_provider + mail_config.', Roles still reads 'Platform-wide role registry. Read-only; add roles via SQL today.' Also new: the Assign client button's tooltip on a user row reads 'Assign clientCode'. 2026-10-13 R4 (build local dev, 2026-10-13): fixed - All three descriptions are clean. Users: 'Assign each user account to a client, deactivate revoked accounts, and audit the changes.' Mail: 'Outbound email provider - pick SMTP, SendGrid, SES or Postmark, edit host/port/creds, and send a live test message.' Roles: 'Platform-wide role registry. Read-only.' The client_code backfill note, the Sprint 50 line, the mail_provider + mail_config note, the 'coming' roadmap list and the 'add roles via SQL today' line have all gone. The Assign client tooltip now reads 'Assign to a client' rather than 'Assign clientCode'. 2026-10-13 R5 (build local dev, 2026-10-13 (rebuilt after R4; frontend modules dated 13:12 IST)): fixed - R5: still clean on the rebuilt build. Users: 'Assign each user account to a client, deactivate revoked accounts, and audit the changes.'; Roles: 'Platform-wide role registry. Read-only.'; Mail: 'Outbound email provider - pick SMTP, SendGrid, SES or Postmark, edit host/port/creds, and send a live test message.' None of the removed notes has come back. | Z50: New
A51: BUG-050 | B51: Medium | C51: Functional | D51: Settings | E51: Organization > Users | F51: Users list | G51: Invite user form (fields, validation, send) | H51: A sent invitation leaves no trace: the invited person is not listed, the audit panel stays empty, and the accept link is shown once and then lost | I51: 1. Open Settings > Users (/settings/users) 2. Click Invite user, enter an address, pick a client and a role, and click Send invite 3. Read the confirmation, then click Done 4. Look at the user list and at 'Recent admin actions' 5. Click Refresh | J51: Invite to qa-1012-invite@example.com, client THB000, role USER. Accept link shown: http://localhost:5173/invite/8881caf518742688c83dfa1d688cecd03d6c748867028fee | K51: The invited person appears in the list as pending, with a way to resend or revoke, and the invitation is recorded in 'Recent admin actions' like any other admin change. | L51: After Done the list still reads 'Showing 2 rows - page 1' with only admin and manoj7000, and 'Recent admin actions' still reads 'No audit entries yet.' A refresh changes nothing. The only copy of the accept link was in the dialog that was just closed, so if the invitation does not arrive there is no way to find it, resend it or cancel it - and no record that it was ever sent. | M51: GET /api/v1/admin/users?page 0&size 50 and GET /api/v1/admin/users/audit?limit 50 both return 200 after the invite, and neither contains the invited address. This matters more here because Settings > Mail reports 'No provider active - outbound emails are logged only', so in this environment no invitation can reach anyone. | N51: http://localhost:5173/settings/users | O51: Always | P51: BUG-050.jpg, BUG-050-2.jpg, BUG-050-3.jpg, BUG-050-4.jpg, BUG-050-5.png, BUG-050-6.jpg, BUG-050-7.jpg, BUG-050-8.jpg, BUG-050-9.jpg, BUG-050-10.png, BUG-050-11.jpg | R51: admin (ADMIN) | T51: 2026-10-12 | U51: R2 | V51: S009 | X51: Closed | Y51: 2026-10-12 R3: still-failing - Half fixed. The invitation is now recorded: 'Recent admin actions' shows '10/12/2026, 6:26:14 PM admin invite_sent qa-1012-retest@example.com' immediately, and the confirmation dialog has gained a 'Copy link' button. The rest is unchanged - after Done the list still reads 'Showing 2 rows - page 1' with only admin and manoj7000, the invited address appears nowhere, there is no pending state and nothing to resend or revoke it with, and the accept link is still gone once the dialog closes. The audit line also prints the raw action code 'invite_sent' rather than words. 2026-10-13 R4 (build local dev, 2026-10-13): fixed - A 'Pending invites (2)' panel has been added below the user list, headed 'Not yet accepted. Resend extends the expiry; Revoke invalidates the link.' Each row shows the address, client, role, who invited and the expiry - for example 'qa-1012-retest@example.com - THB000 - USER - invited by admin - expires 10/19/2026, 6:26:13 PM' - with Copy link, Resend and Revoke. The accept link is recoverable after the dialog is closed, the invitation can be cancelled, and 'Recent admin actions' records each invite. Both leftovers from the earlier runs are now removable from the interface. 2026-10-13 R5 (build local dev, 2026-10-13 (rebuilt after R4; frontend modules dated 13:12 IST)): fixed - Inviting the QA address "qa-1013-r5-<i>x</i>"@example.com (client QA-1013-R5-CL01, role USER) gave POST /api/v1/admin/user-invites -> 201. After Done, 'Pending invites (1)' showed the address, 'QA-1013-R5-CL01 - USER - invited by admin - expires 10/20/2026, 3:50:57 PM' with Copy link ('Accept link copied.'), Resend ('Invite resent and expiry extended.', expiry moved to 3:51:35 PM) and Revoke. Revoke asks 'Please confirm - Revoke the invite for ...? The accept link stops working immediately.'; Cancel sends nothing, Revoke sends DELETE /api/v1/admin/user-invites/5 -> 200 and removes the row. Recent admin actions records the invite. Two new findings came out of this check: BUG-084 (a second invite to the same address issues a second live link) and BUG-085 (resend and revoke are not audited). | Z51: New
A52: BUG-051 | B52: Medium | C52: Security | D52: Settings | E52: Organization > Users | F52: Users list | G52: Row action > Deactivate / Activate | H52: The Deactivate button is enabled on the signed-in admin's own row, and that is the only ADMIN account in the system | I52: 1. Open Settings > Users (/settings/users) 2. Look at the admin row, marked YOU 3. Note that Assign client is disabled ('ADMIN is always org-wide') and the role control reads 'ADMIN (locked)', but Deactivate is live | J52: admin / admin@multiship.local, the only row with role ADMIN | K52: The last remaining ADMIN, and the account the current session belongs to, cannot be deactivated from the interface - the button is disabled with a reason, the way Assign client and the role control already are on this row. | L52: The button is not disabled (disabled=false, no tooltip). If the server does not refuse it, one click would deactivate the only administrator and lock everyone out of the application. | M52: Read from the page, not clicked: the user asked that this not be exercised, because recovery would need database access. Two of the three other controls on the same row are already correctly disabled with explanations, so the guard looks simply to have been missed on this one. Please confirm whether the server refuses it. | N52: http://localhost:5173/settings/users | O52: Not tested | P52: BUG-051.jpg, BUG-051-2.jpg, BUG-051-3.png | R52: admin (ADMIN) | T52: 2026-10-12 | U52: R2 | V52: S009 | X52: Closed | Y52: 2026-10-12 R3: fixed - The Deactivate button on the signed-in admin's own row is now disabled=true with the tooltip "You can't deactivate your own account - ask another admin.", matching Assign client ('ADMIN is always org-wide') and the locked role control. Read from the DOM, not clicked. Note the guard is on self-deactivation; the separate last-remaining-ADMIN case cannot be exercised while admin is the only ADMIN account. 2026-10-13 R4 (build local dev, 2026-10-13): fixed - Deactivate on the signed-in admin's own row reads disabled=true with the tooltip "You can't deactivate your own account - ask another admin." Read from the DOM, not clicked. The separate last-remaining-ADMIN case still cannot be exercised while admin is the only ADMIN account. 2026-10-13 R5 (build local dev, 2026-10-13 (rebuilt after R4; frontend modules dated 13:12 IST)): fixed - On the signed-in admin's own row, Deactivate reads disabled=true with the tooltip 'You can't deactivate your own account - ask another admin.' (read from the page, not clicked). Assign client on the same row is disabled with 'ADMIN is always org-wide'. The last-remaining-ADMIN case still cannot be exercised while admin is the only ADMIN account. | Z52: New
A53: BUG-052 | B53: Medium | C53: Functional | D53: Settings | E53: Organization > Users | F53: Users list | G53: Recent admin actions panel | H53: The user audit trail records nothing: admin changes with a typed reason leave both 'Recent admin actions' and the per-user History empty | I53: 1. Open Settings > Users (/settings/users) 2. Click Assign client on a user, change the client code and type something in 'Reason (optional - recorded in audit)' 3. Click Save and wait for 'Done - Updated manoj7000.' 4. Look at the 'Recent admin actions' panel at the bottom of the page 5. Click Refresh, then click History on that user's row | J53: User manoj7000: client code changed to NOSUCHCLIENT (refused), then saved as THB000 with the reason 'QA-1012 validation check, will be restored'. An invitation to qa-1012-invite@example.com was also sent earlier in the session. | K53: Each admin change is listed, with who made it, when, what changed and the reason given - the page description promises exactly this ('...deactivate revoked accounts, and audit the changes') and the Reason field says it is 'recorded in audit'. | L53: 'Recent admin actions' reads 'No audit entries yet.' before and after the change, and the per-user dialog reads 'No admin actions recorded for this user.' Nothing is recorded for the successful assignment, nor for the invitation sent earlier. | M53: GET /api/v1/admin/users/audit?limit 50 returns 200 after each change, so the page is asking for the list and getting nothing back. The reason text the admin types is therefore collected and discarded. | N53: http://localhost:5173/settings/users | O53: Always | P53: BUG-052.jpg, BUG-052-2.jpg, BUG-052-3.png | R53: admin (ADMIN) | T53: 2026-10-12 | U53: R2 | V53: S009 | X53: Closed | Y53: 2026-10-12 R3: fixed - Assign client on manoj7000 (THB000 -> MKL246) with the reason 'QA retest of BUG-052 audit trail' now appears immediately in 'Recent admin actions' as '10/12/2026, 6:14:49 PM admin moved THB000 -> MKL246 on manoj7000 QA retest of BUG-052 audit trail', and the per-user History dialog 'Audit trail for manoj7000' lists the same entry. The restore back to THB000 was recorded too. Who, when, what changed and the reason are all present. 2026-10-13 R4 (build local dev, 2026-10-13): fixed - Assigning manoj7000 to QA-1013-CL01 with the reason 'QA R4 audit trail check' appeared at once in Recent admin actions as '10/13/2026, 8:13:39 AM admin moved THB000 -> QA-1013-CL01 on manoj7000 QA R4 audit trail check', and the restore to THB000 was recorded the same way. manoj7000 is back on THB000. 2026-10-13 R5 (build local dev, 2026-10-13 (rebuilt after R4; frontend modules dated 13:12 IST)): fixed - Recent admin actions lists the client moves with their reasons (for example '10/13/2026, 8:13:39 AM admin moved THB000 -> QA-1013-CL01 on manoj7000 - QA R4 audit trail check') and the invitations, including the two QA invites sent in this run. History on manoj7000 opens 'Audit trail for manoj7000' with the four client moves and reasons (GET /api/v1/admin/users/2/audit -> 200); History on admin correctly reads 'No admin actions recorded for this user.' Resend and revoke of an invite are still not recorded: logged separately as BUG-085. | Z53: New
A54: BUG-053 | B54: Medium | C54: Functional | D54: Orders | E54: New order | F54: New order form (international) | G54: Client | H54: New shipment: with a single-piece packaging and an extra box still on the form, Validate shipment does nothing at all - no request, no message, no result | I54: 1. Open Orders and click + New shipment (/orders/new) 2. Client MKL246, carrier UPS, ship to QA Test Recipient, 290 Bremner Blvd, Toronto ON M5V 3L9, Canada 3. Service UPS Worldwide Saver, Incoterms DAP, two item lines, importer override Receiver 4. Packaging UPS Large Express Box, then 'Add 1 boxes like the last' so there are two boxes 5. Change Packaging to UPS 10KG Box (a single-piece packaging) - the inline warning appears 6. Click Validate shipment and watch the network tab | J54: MKL246 to Canada, 2 boxes, 2 item lines, UPS 10KG Box | K54: Either the check runs and reports the box-count problem as a failed check, or the Validate button is disabled with the reason, the way Generate label is. Clicking a live button should never be silent. | L54: Nothing happens. POST /api/v1/shipments/validate is never sent, no toast appears, no 'Shipment check' panel opens and no field is marked. The button reports disabled=false and keeps its tooltip, and the console logs no error. All six step chips are green. Switching Packaging back to UPS Large Express Box and clicking the same button immediately sends POST /api/v1/shipments/validate -> 200 and opens the check panel with all five checks Passed, so the form was otherwise complete and only the single-piece conflict silences the button. | M54: Seen while retesting BUG-003. The inline warning next to Packaging reads 'UPS 10KG Box ships at most 1 box per label - the carrier will reject this 2-box shipment. Remove the extra boxes or pick a larger packaging. To ship multiple boxes, create each one as a separate shipment.', so the application knows about the conflict - it just does not say so when the user asks it to check. The same silence was seen with FedEx Envelope. Window 1392x847. | N54: http://localhost:5173/orders/new | O54: Always | P54: Not captured | R54: admin (ADMIN) | T54: 2026-10-12 | U54: R3 | V54: S001 | X54: Closed | Y54: 2026-10-13 R4 (build local dev, 2026-10-13): still-failing - Reproduces on the 2026-10-13 build exactly as first logged. UPS Large Express Box with two boxes, switched to UPS 10KG Box: the inline single-piece warning appears, but Validate shipment sends no POST /api/v1/shipments/validate, raises no toast and opens no check panel. The button reports disabled=false and the console logs nothing. 2026-10-13 R5 (build local dev, 2026-10-13 (rebuilt after R4; frontend modules dated 13:12 IST)): fixed - Validate is no longer silent. Original steps: MKL246 to 290 Bremner Blvd, Toronto ON M5V 3L9, UPS Worldwide Saver, DAP, two item lines spread across two boxes, importer Receiver; Packaging UPS Large Express Box, 'Add 1 boxes like the last', then Packaging changed to UPS 10KG Box (inline warning shown). Clicking Validate shipment now raises the toast 'Too many boxes for this packaging - UPS 10KG Box ships at most 1 box per label - the carrier will reject this 2-box shipment. Remove the extra boxes or pick a larger packaging...'. As before no POST /shipments/validate is sent, which is right since the form already knows the answer. The toast dismisses itself after a few seconds, so a user who looks away can miss it; the inline warning beside Packaging stays. | Z54: Fixed | AB54: Fixed on dev (819f3e57): Single-piece-too-many-boxes gate moved above formik.validateForm 2026-10-12; verified by code review. QA R4 stale FE. | AC54: 2026-10-13
A55: BUG-054 | B55: Medium | C55: Data integrity | D55: Settings | E55: Carriers & Services | F55: Carrier Accounts | H55: Carrier Accounts: the 'Ready to ship 5/5' tile counts every account as ready, including one whose check failed and one that is unverified | I55: 1. Open Settings > Carrier Accounts (/settings/carriers) 2. Read the four summary tiles at the top 3. Read the Status column of the five rows beneath them | J55: The five accounts already on the system, plus QA-1013-CL01's UPS account added during this run | K55: Ready to ship counts only the accounts that can actually produce a label - here 3 of 5 - or the tile says what it is really counting. It should not disagree with the tile beside it. | L55: The first tile reads 'READY TO SHIP 5/5' in green with a tick, while the second reads 'UNVERIFIED 2' in amber with a warning triangle. The rows show USPS/TEST 'Check failed', FedEx 740561111 'Verified', UPS 746W05 'Verified', USPS 874157 'Verified' and UPS QA1013UP 'Unverified'. Three of the five are verified, so 5/5 is wrong by the screen's own data and by the tile next to it. | M55: Read from the rendered table: statuses are 'Check failed', 'Verified', 'Verified', 'Verified', 'Unverified'. A user glancing at the green 5/5 would believe every carrier account is good to go, which is the opposite of what the row for USPS/TEST says. Window 1460x847. | N55: http://localhost:5173/settings/carriers | O55: Always | P55: Not captured | R55: admin (ADMIN) | S55: local dev, 2026-10-13 | T55: 2026-10-13 | U55: R4 | V55: S041 | X55: Closed | Y55: 2026-10-13 R5 (build local dev, 2026-10-13 (rebuilt after R4; frontend modules dated 13:12 IST)): fixed - The tiles now agree with the rows: 'READY TO SHIP 3/5' (FedEx 740561111, UPS 746W05 and USPS 874157 are Verified) beside 'UNVERIFIED 2' (USPS TEST 'Check failed', UPS QA13R5 'Unverified'). Filters > Verification = Verified lists exactly those three. When the QA account was switched Inactive the Unverified tile dropped to 1, and after a failed verification it is counted as Check failed, still outside Ready to ship. | Z55: Fixed | AB55: Fixed on dev (1be9b8a5): Ready to ship tile now requires verified === true so it stops counting Check-failed / Unverified rows. | AC55: 2026-10-13
A56: BUG-055 | B56: High | C56: Security | D56: Settings | E56: Carriers & Services | F56: Carriers (platform) | H56: Carriers (platform): a carrier can be flipped from TEST to LIVE from a plain dropdown in the grid, with no confirmation and no warning that real labels and real charges follow | I56: 1. Open Settings > Carriers (platform) (/settings/carriers-platform) 2. Read the page description and the Mode column 3. Note that Mode is an ordinary select on each row, next to Enable / Disable buttons | J56: The six platform carriers already registered: USPS_DIRECT, FEDEX, STAMPS_COM, USPS, DHL, UPS | K56: Switching a carrier to LIVE is a deliberate, confirmed action - a dialog naming the carrier and what changes, the way Deactivate warehouse and Delete client now do - and the screen says plainly which mode bills real money. A single mis-click on a dropdown should not be able to put the platform into live shipping. | L56: Mode is a bare select on every row with LIVE and TEST as adjacent options and nothing between the click and the change. The page description openly frames it as the point: 'Platform-wide carrier registry - toggle enabled org-wide and flip LIVE/TEST mode without a code deploy.' Four of the six carriers already read LIVE (USPS_DIRECT, FEDEX, STAMPS_COM, UPS) while every carrier account on Settings > Carrier Accounts is SANDBOX, so the two screens disagree about which environment the platform is in. | M56: Read from the screen, not exercised: changing a carrier to LIVE on a system wired to real carrier accounts could buy real labels and incur real charges, so the control was deliberately not operated. Please confirm what the server does with the change and whether any confirmation exists behind it. Window 1460x847. | N56: http://localhost:5173/settings/carriers-platform | O56: Not tested | P56: Not captured | R56: admin (ADMIN) | S56: local dev, 2026-10-13 | T56: 2026-10-13 | U56: R4 | V56: S042 | X56: Closed | Y56: 2026-10-13 R5 (build local dev, 2026-10-13 (rebuilt after R4; frontend modules dated 13:12 IST)): fixed - Checked with every write from the page blocked first, as agreed. Picking LIVE on the USPS row now opens 'Enable LIVE for USPS? - LIVE mode produces real labels and real carrier charges from this carrier's production account. Make sure every connected tenant is ready before switching.' with Cancel and a red 'Enable LIVE'; picking TEST on UPS opens 'Return UPS to TEST? - New shipments will hit the sandbox from now on. In-flight production shipments are not affected.' Cancel returns the select to its old value and sends nothing; a Refresh shows all six modes unchanged. Disable on FedEx also asks ('Disable FEDEX org-wide?'). Still worth a look, though no longer part of this bug: four platform carriers read LIVE while every carrier account on Carrier Accounts is SANDBOX. | Z56: Fixed | AB56: Fixed on dev (cc9e5bcf): LIVE/TEST flip now confirms with carrier name + consequence; danger-styled when going to LIVE. Backend already @PreAuthorize(hasRole ADMIN). | AC56: 2026-10-13
A57: BUG-056 | B57: Low | C57: Usability | D57: Settings | E57: Carriers & Services | F57: Code Maps | H57: Code Maps: 'Add alias' stays greyed with no tooltip, no marked field and no message, so there is nothing on screen saying what is missing | I57: 1. Open Settings > Code Maps (/settings/code-maps) with client MKL246 selected 2. On the Shipvia tab, click + Add alias with the form empty 3. Type QA13 into ERP SHIPVIA CODE and look at the button again | J57: Client MKL246, ERP shipvia code QA13, Platform service left unset | K57: Either the button says why it is unavailable - a tooltip, or the unfilled field marked with its message, the way the client wizard's 'Add to list' now does - or clicking it marks what is missing. | L57: The button reports disabled=true with no title attribute at all. Clicking it does nothing: no toast, no field marked, no hint text anywhere on the panel. With a code typed but Platform service still unset it stays disabled and still explains nothing. The user has to guess that the service dropdown is the blocker. | M57: Read from the DOM: the Add alias button has disabled=true and no title. This is the same fault that was reported as BUG-031 on the client wizard and fixed there - the fix was not carried across to this screen. Window 1460x847. | N57: http://localhost:5173/settings/code-maps | O57: Always | P57: Not captured | R57: admin (ADMIN) | S57: local dev, 2026-10-13 | T57: 2026-10-13 | U57: R4 | V57: S044 | X57: Closed | Y57: 2026-10-13 R5 (build local dev, 2026-10-13 (rebuilt after R4; frontend modules dated 13:12 IST)): fixed - Add alias now explains itself while disabled: with the form empty its tooltip reads 'Fill an ERP code + a platform target to add the alias.', with a code typed but no service 'Fill a platform target to add the alias.', and on the Destination country tab 'Fill an ERP code + a 2-letter ISO country to add the alias.' Once both are filled the button enables and saves ('Shipvia alias saved.'). | Z57: Fixed | AB57: Fixed on dev (0e738838): Code Maps Add alias button gets a context-aware tooltip listing missing fields (same pattern as the client wizard Add-to-list). | AC57: 2026-10-13
A58: BUG-057 | B58: Low | C58: Content | D58: Settings | E58: Carriers & Services | F58: Carrier Dropdowns | H58: Carrier Dropdowns says it is the vocabulary /orders/new uses, but the order form shows different wording for the same carrier and code | I58: 1. Open Settings > Carrier Dropdowns (/settings/carrier-dropdowns) and read the Label formats tab 2. Note the FEDEX rows: code PDF -> 'PDF (plain)' and code ZPLII -> 'ZPL (thermal)' 3. Open Orders > + New shipment, pick client MKL246 and carrier FedEx 4. Open the Label type dropdown and read the options | J58: Client MKL246, carrier FedEx | K58: The order form shows the labels this registry defines, since the page describes itself as the vocabulary that form uses. | L58: The registry lists FEDEX / PDF as 'PDF (plain)' and FEDEX / ZPLII as 'ZPL (thermal)'. The order form offers 'PDF (vector, sharp)' and 'ZPLII (Zebra)' for the same carrier. With USPS selected the form does show 'PDF (plain)', matching the registry, so the two agree for one carrier and disagree for another. Either the form is not reading this table for FedEx or the table is not the source it claims to be. | M58: The page description reads 'Per-carrier vocabularies the /orders/new wizard uses - label formats, pickup types, clearance options. Read-only.' Compared against the Label type dropdown on the New shipment form in the same session. Window 1460x847. | N58: http://localhost:5173/settings/carrier-dropdowns | O58: Always | P58: BUG-057-R7-registry.jpg, BUG-057-R7.jpg | R58: admin (ADMIN) | S58: local dev, 2026-10-13 | T58: 2026-10-13 | U58: R4 | V58: S046 | W58: Orders > New order > New order form (international); Settings > Carriers & Services > Carrier Accounts | X58: Closed | Y58: 2026-10-13 R5 (build local dev, 2026-10-13 (rebuilt after R4; frontend modules dated 13:12 IST)): still-failing - Partly fixed. The two labels named in the bug now match: the order form (Orders > New shipment, MKL246, FedEx) offers 'PDF (plain)' and 'ZPL (thermal)' (code ZPLII), as the registry does. But the FedEx list still differs from the FEDEX rows on Carrier Dropdowns > Label formats: the form shows PNG as 'PNG (raster)' where the registry says 'PNG (plain)', and it offers EPL2 'EPL (Eltron/legacy Zebra)' and DPL 'DPL (Datamax)', which the registry does not list for FedEx, while the registry's COMMON2D 'Common 2D (stock)' and LABEL_DATA_ONLY 'Label data only' are not offered. UPS and USPS now match the registry exactly (UPS: GIF (stock), PDF (plain), PNG (plain), ZPL (thermal), EPL; USPS: PDF, ZPL, PNG, JPG). Settings > Carrier Accounts > UPS 'Label image format' also uses its own wording ('PDF (vector, sharp)', 'PNG (raster)', 'ZPL (Zebra)'). 2026-10-14 R6 (build local dev, 2026-10-14 (order-form modules reloaded 13:17 IST)): still-failing - R6: unchanged. Carrier Dropdowns > Label formats lists FEDEX as COMMON2D 'Common 2D (stock)', LABEL_DATA_ONLY 'Label data only', PDF 'PDF (plain)', PNG 'PNG (plain)' and ZPLII 'ZPL (thermal)'. The order form (MKL246, FedEx, today) offers PDF (plain), PNG (raster), ZPL (thermal), EPL (Eltron/legacy Zebra) and DPL (Datamax) - PNG worded differently, EPL2 and DPL offered although not in the registry, COMMON2D and LABEL_DATA_ONLY missing. 2026-10-16 R7 (build local dev, 2026-10-16): fixed - R7: the order form now offers exactly the registry's rows for every carrier. Orders > + New shipment, MKL246: FedEx Label type = Common 2D (stock), Label data only, PDF (plain), PNG (plain), ZPL (thermal) [ZPLII]; UPS = GIF (stock), PDF (plain), PNG (plain), ZPL (thermal), EPL (Eltron/legacy Zebra); USPS = PDF (plain), ZPL (thermal), PNG (plain), JPG (raster) - the same code/label pairs as Settings > Carrier Dropdowns > Label formats (R6: PNG (raster), EPL and DPL offered for FedEx, COMMON2D and LABEL_DATA_ONLY missing). The FedEx account editor reads the registry too. Not yet in step: the UPS and USPS account editors keep their own wording - raised as BUG-153. | Z58: Fixed | AB58: Fixed on dev (839f1ef8): FEDEX order form + per-carrier editor modals now read labelFormatsForCarrier() (DB registry); FEDEX added to the bootstrap list to mirror V120 seed. Test fix (46d6db84, 2026-10-15): — no code change, just test lock-in. | AC58: 2026-10-15
A59: BUG-058 | B59: Medium | C59: Usability | D59: Settings | E59: Carriers & Services | F59: Cutoffs & Holidays | H59: Cutoffs & Holidays: a holiday and a cutoff rule are both deleted on a single click of the trash icon, with no confirmation | I59: 1. Open Settings > Cutoffs & Holidays (/settings/cutoffs) 2. Scroll to Global holiday list and add a row - date 27-11-2026, name 'QA-1013 Test Holiday' - with + Add 3. Click the trash icon on that row 4. Note that the row is gone immediately, and that the Cutoff rules grid above offers the same single-click trash on each of its 17 rows | J59: QA-1013 Test Holiday on 2026-11-27, created and deleted during this run | K59: Deleting a date that changes when every shipment's SHIP_DATE rolls forward is confirmed first, the way deleting a warehouse or a client now is - a dialog naming the row and what depends on it. | L59: One click removes the row. No dialog, no named confirmation, and no undo. The same trash icon sits on all 17 cutoff rules directly above, one row apart from the four real holidays (New Year's Day, Christmas Eve, and the same two for next year), so a mis-click silently changes the platform's working-day calendar. By contrast the delete flows on Clients, Warehouses and user invitations all confirm. | M59: Exercised on a test row only - no real holiday or cutoff rule was deleted. The page itself explains the stakes: 'Dates the cutoff logic treats as non-working when advancing to the next working day' and 'Shipments past cutoff or on a holiday get their SHIP_DATE pushed to the next working day.' Window 1460x847. | N59: http://localhost:5173/settings/cutoffs | O59: Always | P59: Not captured | R59: admin (ADMIN) | S59: local dev, 2026-10-13 | T59: 2026-10-13 | U59: R4 | V59: S047 | X59: Closed | Y59: 2026-10-13 R5 (build local dev, 2026-10-13 (rebuilt after R4; frontend modules dated 13:12 IST)): fixed - Both trash icons now confirm. A QA holiday (27-11-2026 'QA-1013-R5 Test Holiday <i>x</i>') asks 'Delete holiday? ... (2026-11-27)? Removing a holiday changes which day the cutoff rules treat as the next working day. Shipments due that day will no longer roll forward.'; Cancel kept it, Delete removed it (DELETE /api/v1/admin/cutoffs/holidays/6). A real cutoff rule's trash asks 'Delete cutoff rule #16? Source: WMS - Carrier: UPS - Warehouse: 1. Shipments that match this rule will roll forward using the next-matching rule or the platform default.' - answered Cancel, nothing sent, 17 rules intact. | Z59: Fixed | AB59: Fixed on dev (5625dc84): Cutoffs + Holidays trash icon now uses notify.confirm with rule context + consequence. | AC59: 2026-10-13
A60: BUG-059 | B60: High | C60: Usability | D60: Settings | E60: Carriers & Services | F60: Pickups & End-of-Day | H60: Pickups & End-of-Day: 'Close out' is a single unguarded button that closes every open label for a carrier and date, and it defaults to all clients | I60: 1. Open Settings > Pickups & End-of-Day (/settings/pickups) 2. Read the End-of-day close panel: Carrier FEDEX, Close date today, Client 'All clients', Warehouse code optional 3. Read the paragraph beneath it, then look at the Close out button | J60: Not exercised - the defaults would have closed every open FedEx label for 13-10-2026 across all clients | K60: A bulk, carrier-facing, irreversible action is confirmed first, and says how many labels it is about to close and for which client - the way Deactivate warehouse now names the client count. | L60: The panel opens pre-filled with Carrier FEDEX, Close date 13-10-2026 and Client 'All clients', and offers one full-width black 'Close out' button. Its own description says what is at stake: 'Closes every open (generated, non-voided) label for the chosen carrier on that date. To close only specific orders instead, Close out on the Orders page.' Nothing on the screen states how many labels that is, and there is no confirmation step between the click and the carrier call. | M60: Read from the screen, not exercised: closing out a day against a carrier account is not reversible from this interface and affects every open label, so the button was deliberately not pressed. 'Schedule a pickup' in the panel beside it is the same shape - a carrier-facing booking with no confirmation step visible. Please confirm whether the server asks anything before acting. Window 1460x847. | N60: http://localhost:5173/settings/pickups | O60: Not tested | P60: Not captured | R60: admin (ADMIN) | S60: local dev, 2026-10-13 | T60: 2026-10-13 | U60: R4 | V60: S048 | X60: Closed | Y60: 2026-10-13 R5 (build local dev, 2026-10-13 (rebuilt after R4; frontend modules dated 13:12 IST)): fixed - Checked with every write from the page blocked first, as agreed. Close out now opens 'Close out FEDEX 2026-10-13? ... Scope: EVERY client. This files the end-of-day manifest with the carrier and closes every open (generated, non-voided) label in scope. It cannot be undone from this screen.' with Cancel and a red Close out; with client QA-1013-R5-CL01 picked the scope line reads 'Scope: client QA-1013-R5-CL01'. Cancel sent nothing both times and Recent activity still reads 'No pickups or close-outs yet.' The panel still opens on All clients and the dialog does not say how many labels will be closed, which the bug also asked for; the unguarded click itself is gone. | Z60: Fixed | AB60: Fixed on dev (33d51c1e): End-of-day Close out confirms with carrier + date + scope (All clients vs specific). | AC60: 2026-10-13
A61: BUG-060 | B61: Medium | C61: Data integrity | D61: Settings | E61: International | F61: Countries | H61: Two Settings screens claim to hold an international standard list but hold a small subset: Countries shows only the six US territories, Currencies only ten currencies | I61: 1. Open Settings > Countries (/settings/countries) 2. Read the heading and description 3. Count the rows | J61: No test data needed - the screen is read-only | K61: Either the screen lists the ISO countries the rest of Settings validates against, or it is named for what it actually holds - the US-territory flags. | L61: Countries: six rows - PR Puerto Rico, VI US Virgin Islands, GU Guam, AS American Samoa, MP Northern Mariana Islands, UM US Minor Outlying Islands - every one flagged 'US territory: yes', under the description 'ISO country list + is_us_territory flag.' There is no ISO country list here. Currencies: ten rows - USD, EUR, GBP, CAD, INR, AUD, SGD, JPY, CNY, AED - under 'ISO 4217 currency catalog', which has about 180 entries. This is the root of BUG-046: with no master country list on this screen, the address book carries its own 250-entry select, the client wizard its own searchable combobox and the warehouse panel a free-typed ISO-2 box that is checked against nothing. | M61: Counted from the rendered table: 6 rows. Compare BUG-046, where the same field is built three different ways elsewhere in Settings. Window 1460x847. | N61: http://localhost:5173/settings/countries | O61: Always | P61: Not captured | R61: admin (ADMIN) | S61: local dev, 2026-10-13 | T61: 2026-10-13 | U61: R4 | V61: S050 | W61: Settings > International > Countries; Settings > International > Currencies | X61: Closed | Y61: 2026-10-13 R5 (build local dev, 2026-10-13 (rebuilt after R4; frontend modules dated 13:12 IST)): fixed - Both lists now hold the standard sets. Settings > Countries lists 249 ISO 3166-1 countries (no duplicate codes, US included) with the six US territories still flagged 'yes' and listed first, under 'ISO country list with US-territory flag. Read-only.' Settings > Currencies lists 178 ISO 4217 currencies (USD ... ZWG, three-letter codes, no duplicates). The shared country picker on the order, warehouse, address-book and client screens still offers its own shorter list - that part is tracked in BUG-046. | Z61: Fixed | AB61: Fixed on dev (V151 + V152): V151 seeds 249 ISO 3166-1 countries (US-territory flags preserved); V152 seeds 178 ISO 4217 currencies. | AC61: 2026-10-13
